<?xml version="1.0" standalone="yes"?>
<NewDataSet>
  <xs:schema id="NewDataSet" xmlns="" xmlns:xs="http://www.w3.org/2001/XMLSchema" xmlns:msdata="urn:schemas-microsoft-com:xml-msdata">
    <xs:element name="NewDataSet" msdata:IsDataSet="true" msdata:MainDataTable="marketintervaldetail" msdata:UseCurrentLocale="true">
      <xs:complexType>
        <xs:choice minOccurs="0" maxOccurs="unbounded">
          <xs:element name="marketintervaldetail">
            <xs:complexType>
              <xs:sequence>
                <xs:element name="Data" type="xs:string" minOccurs="0" />
                <xs:element name="Mercato" type="xs:string" minOccurs="0" />
                <xs:element name="Ora" type="xs:string" minOccurs="0" />
                <xs:element name="Totale" type="xs:string" minOccurs="0" />
                <xs:element name="CALA" type="xs:string" minOccurs="0" />
                <xs:element name="CNOR" type="xs:string" minOccurs="0" />
                <xs:element name="CSUD" type="xs:string" minOccurs="0" />
                <xs:element name="NORD" type="xs:string" minOccurs="0" />
                <xs:element name="SARD" type="xs:string" minOccurs="0" />
                <xs:element name="SICI" type="xs:string" minOccurs="0" />
                <xs:element name="SUD" type="xs:string" minOccurs="0" />
              </xs:sequence>
            </xs:complexType>
          </xs:element>
        </xs:choice>
      </xs:complexType>
    </xs:element>
  </xs:schema>
  <marketintervaldetail>
    <Data>20210312</Data>
    <Mercato>MGP</Mercato>
    <Ora>01</Ora>
    <Totale>27008</Totale>
    <CALA>510</CALA>
    <CNOR>2168</CNOR>
    <CSUD>4500</CSUD>
    <NORD>15645</NORD>
    <SARD>796</SARD>
    <SICI>1593</SICI>
    <SUD>1796</SUD>
  </marketintervaldetail>
  <marketintervaldetail>
    <Data>20210312</Data>
    <Mercato>MGP</Mercato>
    <Ora>02</Ora>
    <Totale>25585</Totale>
    <CALA>482</CALA>
    <CNOR>2060</CNOR>
    <CSUD>4259</CSUD>
    <NORD>14864</NORD>
    <SARD>738</SARD>
    <SICI>1443</SICI>
    <SUD>1739</SUD>
  </marketintervaldetail>
  <marketintervaldetail>
    <Data>20210312</Data>
    <Mercato>MGP</Mercato>
    <Ora>03</Ora>
    <Totale>24637</Totale>
    <CALA>452</CALA>
    <CNOR>1979</CNOR>
    <CSUD>4040</CSUD>
    <NORD>14402</NORD>
    <SARD>712</SARD>
    <SICI>1363</SICI>
    <SUD>1689</SUD>
  </marketintervaldetail>
  <marketintervaldetail>
    <Data>20210312</Data>
    <Mercato>MGP</Mercato>
    <Ora>04</Ora>
    <Totale>24242</Totale>
    <CALA>445</CALA>
    <CNOR>1969</CNOR>
    <CSUD>3941</CSUD>
    <NORD>14176</NORD>
    <SARD>703</SARD>
    <SICI>1306</SICI>
    <SUD>1702</SUD>
  </marketintervaldetail>
  <marketintervaldetail>
    <Data>20210312</Data>
    <Mercato>MGP</Mercato>
    <Ora>05</Ora>
    <Totale>24749</Totale>
    <CALA>442</CALA>
    <CNOR>2019</CNOR>
    <CSUD>4097</CSUD>
    <NORD>14484</NORD>
    <SARD>717</SARD>
    <SICI>1337</SICI>
    <SUD>1653</SUD>
  </marketintervaldetail>
  <marketintervaldetail>
    <Data>20210312</Data>
    <Mercato>MGP</Mercato>
    <Ora>06</Ora>
    <Totale>26819</Totale>
    <CALA>528</CALA>
    <CNOR>2166</CNOR>
    <CSUD>4366</CSUD>
    <NORD>15805</NORD>
    <SARD>750</SARD>
    <SICI>1443</SICI>
    <SUD>1761</SUD>
  </marketintervaldetail>
  <marketintervaldetail>
    <Data>20210312</Data>
    <Mercato>MGP</Mercato>
    <Ora>07</Ora>
    <Totale>31136</Totale>
    <CALA>541</CALA>
    <CNOR>2510</CNOR>
    <CSUD>5055</CSUD>
    <NORD>18832</NORD>
    <SARD>803</SARD>
    <SICI>1553</SICI>
    <SUD>1842</SUD>
  </marketintervaldetail>
  <marketintervaldetail>
    <Data>20210312</Data>
    <Mercato>MGP</Mercato>
    <Ora>08</Ora>
    <Totale>36035</Totale>
    <CALA>571</CALA>
    <CNOR>2952</CNOR>
    <CSUD>5842</CSUD>
    <NORD>21975</NORD>
    <SARD>931</SARD>
    <SICI>1776</SICI>
    <SUD>1988</SUD>
  </marketintervaldetail>
  <marketintervaldetail>
    <Data>20210312</Data>
    <Mercato>MGP</Mercato>
    <Ora>09</Ora>
    <Totale>40397</Totale>
    <CALA>677</CALA>
    <CNOR>3589</CNOR>
    <CSUD>6698</CSUD>
    <NORD>24206</NORD>
    <SARD>1042</SARD>
    <SICI>1911</SICI>
    <SUD>2274</SUD>
  </marketintervaldetail>
  <marketintervaldetail>
    <Data>20210312</Data>
    <Mercato>MGP</Mercato>
    <Ora>10</Ora>
    <Totale>41755</Totale>
    <CALA>630</CALA>
    <CNOR>3829</CNOR>
    <CSUD>7291</CSUD>
    <NORD>24861</NORD>
    <SARD>1057</SARD>
    <SICI>1893</SICI>
    <SUD>2194</SUD>
  </marketintervaldetail>
  <marketintervaldetail>
    <Data>20210312</Data>
    <Mercato>MGP</Mercato>
    <Ora>11</Ora>
    <Totale>41357</Totale>
    <CALA>612</CALA>
    <CNOR>3836</CNOR>
    <CSUD>7476</CSUD>
    <NORD>24295</NORD>
    <SARD>988</SARD>
    <SICI>1923</SICI>
    <SUD>2227</SUD>
  </marketintervaldetail>
  <marketintervaldetail>
    <Data>20210312</Data>
    <Mercato>MGP</Mercato>
    <Ora>12</Ora>
    <Totale>40816</Totale>
    <CALA>628</CALA>
    <CNOR>3718</CNOR>
    <CSUD>7379</CSUD>
    <NORD>24121</NORD>
    <SARD>1003</SARD>
    <SICI>1956</SICI>
    <SUD>2011</SUD>
  </marketintervaldetail>
  <marketintervaldetail>
    <Data>20210312</Data>
    <Mercato>MGP</Mercato>
    <Ora>13</Ora>
    <Totale>39720</Totale>
    <CALA>657</CALA>
    <CNOR>3433</CNOR>
    <CSUD>7247</CSUD>
    <NORD>23216</NORD>
    <SARD>1031</SARD>
    <SICI>1930</SICI>
    <SUD>2206</SUD>
  </marketintervaldetail>
  <marketintervaldetail>
    <Data>20210312</Data>
    <Mercato>MGP</Mercato>
    <Ora>14</Ora>
    <Totale>38136</Totale>
    <CALA>598</CALA>
    <CNOR>3317</CNOR>
    <CSUD>7063</CSUD>
    <NORD>22286</NORD>
    <SARD>960</SARD>
    <SICI>1740</SICI>
    <SUD>2172</SUD>
  </marketintervaldetail>
  <marketintervaldetail>
    <Data>20210312</Data>
    <Mercato>MGP</Mercato>
    <Ora>15</Ora>
    <Totale>38762</Totale>
    <CALA>548</CALA>
    <CNOR>3378</CNOR>
    <CSUD>6964</CSUD>
    <NORD>23133</NORD>
    <SARD>961</SARD>
    <SICI>1726</SICI>
    <SUD>2052</SUD>
  </marketintervaldetail>
  <marketintervaldetail>
    <Data>20210312</Data>
    <Mercato>MGP</Mercato>
    <Ora>16</Ora>
    <Totale>39117</Totale>
    <CALA>607</CALA>
    <CNOR>3461</CNOR>
    <CSUD>6971</CSUD>
    <NORD>23193</NORD>
    <SARD>1023</SARD>
    <SICI>1827</SICI>
    <SUD>2035</SUD>
  </marketintervaldetail>
  <marketintervaldetail>
    <Data>20210312</Data>
    <Mercato>MGP</Mercato>
    <Ora>17</Ora>
    <Totale>39174</Totale>
    <CALA>621</CALA>
    <CNOR>3432</CNOR>
    <CSUD>7012</CSUD>
    <NORD>23126</NORD>
    <SARD>1045</SARD>
    <SICI>1828</SICI>
    <SUD>2110</SUD>
  </marketintervaldetail>
  <marketintervaldetail>
    <Data>20210312</Data>
    <Mercato>MGP</Mercato>
    <Ora>18</Ora>
    <Totale>39375</Totale>
    <CALA>698</CALA>
    <CNOR>3490</CNOR>
    <CSUD>7017</CSUD>
    <NORD>22876</NORD>
    <SARD>1005</SARD>
    <SICI>2007</SICI>
    <SUD>2282</SUD>
  </marketintervaldetail>
  <marketintervaldetail>
    <Data>20210312</Data>
    <Mercato>MGP</Mercato>
    <Ora>19</Ora>
    <Totale>40634</Totale>
    <CALA>845</CALA>
    <CNOR>3536</CNOR>
    <CSUD>7232</CSUD>
    <NORD>23153</NORD>
    <SARD>1090</SARD>
    <SICI>2302</SICI>
    <SUD>2476</SUD>
  </marketintervaldetail>
  <marketintervaldetail>
    <Data>20210312</Data>
    <Mercato>MGP</Mercato>
    <Ora>20</Ora>
    <Totale>42114</Totale>
    <CALA>903</CALA>
    <CNOR>3598</CNOR>
    <CSUD>7439</CSUD>
    <NORD>23894</NORD>
    <SARD>1196</SARD>
    <SICI>2512</SICI>
    <SUD>2572</SUD>
  </marketintervaldetail>
  <marketintervaldetail>
    <Data>20210312</Data>
    <Mercato>MGP</Mercato>
    <Ora>21</Ora>
    <Totale>39132</Totale>
    <CALA>832</CALA>
    <CNOR>3295</CNOR>
    <CSUD>7016</CSUD>
    <NORD>21848</NORD>
    <SARD>1173</SARD>
    <SICI>2475</SICI>
    <SUD>2493</SUD>
  </marketintervaldetail>
  <marketintervaldetail>
    <Data>20210312</Data>
    <Mercato>MGP</Mercato>
    <Ora>22</Ora>
    <Totale>35735</Totale>
    <CALA>770</CALA>
    <CNOR>2998</CNOR>
    <CSUD>6397</CSUD>
    <NORD>19964</NORD>
    <SARD>1093</SARD>
    <SICI>2262</SICI>
    <SUD>2251</SUD>
  </marketintervaldetail>
  <marketintervaldetail>
    <Data>20210312</Data>
    <Mercato>MGP</Mercato>
    <Ora>23</Ora>
    <Totale>32233</Totale>
    <CALA>712</CALA>
    <CNOR>2688</CNOR>
    <CSUD>5763</CSUD>
    <NORD>18050</NORD>
    <SARD>1007</SARD>
    <SICI>2032</SICI>
    <SUD>1981</SUD>
  </marketintervaldetail>
  <marketintervaldetail>
    <Data>20210312</Data>
    <Mercato>MGP</Mercato>
    <Ora>24</Ora>
    <Totale>29450</Totale>
    <CALA>643</CALA>
    <CNOR>2484</CNOR>
    <CSUD>5154</CSUD>
    <NORD>16594</NORD>
    <SARD>930</SARD>
    <SICI>1826</SICI>
    <SUD>1819</SUD>
  </marketintervaldetail>
</NewDataSet>