<?xml version="1.0" standalone="yes"?>
<NewDataSet>
  <xs:schema id="NewDataSet" xmlns="" xmlns:xs="http://www.w3.org/2001/XMLSchema" xmlns:msdata="urn:schemas-microsoft-com:xml-msdata">
    <xs:element name="NewDataSet" msdata:IsDataSet="true" msdata:UseCurrentLocale="true">
      <xs:complexType>
        <xs:choice minOccurs="0" maxOccurs="unbounded">
          <xs:element name="Fabbisogno">
            <xs:complexType>
              <xs:sequence>
                <xs:element name="Data" type="xs:string" minOccurs="0" />
                <xs:element name="Mercato" type="xs:string" minOccurs="0" />
                <xs:element name="Ora" type="xs:string" minOccurs="0" />
                <xs:element name="Italia" type="xs:string" minOccurs="0" />
                <xs:element name="CNOR" type="xs:string" minOccurs="0" />
                <xs:element name="CSUD" type="xs:string" minOccurs="0" />
                <xs:element name="NORD" type="xs:string" minOccurs="0" />
                <xs:element name="SARD" type="xs:string" minOccurs="0" />
                <xs:element name="SICI" type="xs:string" minOccurs="0" />
                <xs:element name="SUD" type="xs:string" minOccurs="0" />
              </xs:sequence>
            </xs:complexType>
          </xs:element>
        </xs:choice>
      </xs:complexType>
    </xs:element>
  </xs:schema>
  <Fabbisogno>
    <Data>20180328</Data>
    <Mercato>MGP</Mercato>
    <Ora>1</Ora>
    <Italia>28416,137</Italia>
    <CNOR>2910,307</CNOR>
    <CSUD>4349,753</CSUD>
    <NORD>16278,327</NORD>
    <SARD>867,707</SARD>
    <SICI>1746,496</SICI>
    <SUD>2263,547</SUD>
  </Fabbisogno>
  <Fabbisogno>
    <Data>20180328</Data>
    <Mercato>MGP</Mercato>
    <Ora>2</Ora>
    <Italia>26818,146</Italia>
    <CNOR>2732,724</CNOR>
    <CSUD>3990,528</CSUD>
    <NORD>15596,656</NORD>
    <SARD>805,241</SARD>
    <SICI>1594,005</SICI>
    <SUD>2098,992</SUD>
  </Fabbisogno>
  <Fabbisogno>
    <Data>20180328</Data>
    <Mercato>MGP</Mercato>
    <Ora>3</Ora>
    <Italia>25999,386</Italia>
    <CNOR>2652,699</CNOR>
    <CSUD>3809,539</CSUD>
    <NORD>15215,953</NORD>
    <SARD>776,187</SARD>
    <SICI>1515,487</SICI>
    <SUD>2029,521</SUD>
  </Fabbisogno>
  <Fabbisogno>
    <Data>20180328</Data>
    <Mercato>MGP</Mercato>
    <Ora>4</Ora>
    <Italia>25775,45</Italia>
    <CNOR>2639,841</CNOR>
    <CSUD>3741,004</CSUD>
    <NORD>15124,311</NORD>
    <SARD>774,111</SARD>
    <SICI>1487,37</SICI>
    <SUD>2008,813</SUD>
  </Fabbisogno>
  <Fabbisogno>
    <Data>20180328</Data>
    <Mercato>MGP</Mercato>
    <Ora>5</Ora>
    <Italia>25987,002</Italia>
    <CNOR>2640,451</CNOR>
    <CSUD>3753,489</CSUD>
    <NORD>15322,332</NORD>
    <SARD>768,856</SARD>
    <SICI>1484,875</SICI>
    <SUD>2016,999</SUD>
  </Fabbisogno>
  <Fabbisogno>
    <Data>20180328</Data>
    <Mercato>MGP</Mercato>
    <Ora>6</Ora>
    <Italia>27544,988</Italia>
    <CNOR>2809,868</CNOR>
    <CSUD>3998,039</CSUD>
    <NORD>16276,642</NORD>
    <SARD>803,825</SARD>
    <SICI>1558,228</SICI>
    <SUD>2098,386</SUD>
  </Fabbisogno>
  <Fabbisogno>
    <Data>20180328</Data>
    <Mercato>MGP</Mercato>
    <Ora>7</Ora>
    <Italia>31758,646</Italia>
    <CNOR>3234,998</CNOR>
    <CSUD>4545,245</CSUD>
    <NORD>19126,582</NORD>
    <SARD>904,256</SARD>
    <SICI>1697,759</SICI>
    <SUD>2249,806</SUD>
  </Fabbisogno>
  <Fabbisogno>
    <Data>20180328</Data>
    <Mercato>MGP</Mercato>
    <Ora>8</Ora>
    <Italia>37064,957</Italia>
    <CNOR>3831,563</CNOR>
    <CSUD>5423,749</CSUD>
    <NORD>22041,317</NORD>
    <SARD>1052,624</SARD>
    <SICI>2046,047</SICI>
    <SUD>2669,657</SUD>
  </Fabbisogno>
  <Fabbisogno>
    <Data>20180328</Data>
    <Mercato>MGP</Mercato>
    <Ora>9</Ora>
    <Italia>41547,548</Italia>
    <CNOR>4441,465</CNOR>
    <CSUD>5996,522</CSUD>
    <NORD>24754,477</NORD>
    <SARD>1164,431</SARD>
    <SICI>2237,989</SICI>
    <SUD>2952,664</SUD>
  </Fabbisogno>
  <Fabbisogno>
    <Data>20180328</Data>
    <Mercato>MGP</Mercato>
    <Ora>10</Ora>
    <Italia>42034,76</Italia>
    <CNOR>4548,243</CNOR>
    <CSUD>6178,311</CSUD>
    <NORD>24947,893</NORD>
    <SARD>1136,574</SARD>
    <SICI>2263,268</SICI>
    <SUD>2960,471</SUD>
  </Fabbisogno>
  <Fabbisogno>
    <Data>20180328</Data>
    <Mercato>MGP</Mercato>
    <Ora>11</Ora>
    <Italia>41139,176</Italia>
    <CNOR>4463,03</CNOR>
    <CSUD>6112,266</CSUD>
    <NORD>24446,448</NORD>
    <SARD>1073,804</SARD>
    <SICI>2181,469</SICI>
    <SUD>2862,159</SUD>
  </Fabbisogno>
  <Fabbisogno>
    <Data>20180328</Data>
    <Mercato>MGP</Mercato>
    <Ora>12</Ora>
    <Italia>40354,118</Italia>
    <CNOR>4384,394</CNOR>
    <CSUD>6020,506</CSUD>
    <NORD>23976,893</NORD>
    <SARD>1033,97</SARD>
    <SICI>2128,114</SICI>
    <SUD>2810,241</SUD>
  </Fabbisogno>
  <Fabbisogno>
    <Data>20180328</Data>
    <Mercato>MGP</Mercato>
    <Ora>13</Ora>
    <Italia>38023,194</Italia>
    <CNOR>4074,719</CNOR>
    <CSUD>5887,689</CSUD>
    <NORD>22119,151</NORD>
    <SARD>1019,113</SARD>
    <SICI>2110,188</SICI>
    <SUD>2812,334</SUD>
  </Fabbisogno>
  <Fabbisogno>
    <Data>20180328</Data>
    <Mercato>MGP</Mercato>
    <Ora>14</Ora>
    <Italia>37610,951</Italia>
    <CNOR>3903,798</CNOR>
    <CSUD>5691,642</CSUD>
    <NORD>22300,566</NORD>
    <SARD>967,13</SARD>
    <SICI>2050,468</SICI>
    <SUD>2697,347</SUD>
  </Fabbisogno>
  <Fabbisogno>
    <Data>20180328</Data>
    <Mercato>MGP</Mercato>
    <Ora>15</Ora>
    <Italia>38460,432</Italia>
    <CNOR>4113,193</CNOR>
    <CSUD>5810,388</CSUD>
    <NORD>22847,788</NORD>
    <SARD>958,767</SARD>
    <SICI>2067,175</SICI>
    <SUD>2663,121</SUD>
  </Fabbisogno>
  <Fabbisogno>
    <Data>20180328</Data>
    <Mercato>MGP</Mercato>
    <Ora>16</Ora>
    <Italia>39044,124</Italia>
    <CNOR>4194,549</CNOR>
    <CSUD>5884,964</CSUD>
    <NORD>23162,105</NORD>
    <SARD>966,707</SARD>
    <SICI>2104,391</SICI>
    <SUD>2731,408</SUD>
  </Fabbisogno>
  <Fabbisogno>
    <Data>20180328</Data>
    <Mercato>MGP</Mercato>
    <Ora>17</Ora>
    <Italia>39330,128</Italia>
    <CNOR>4275,801</CNOR>
    <CSUD>5937,631</CSUD>
    <NORD>23065,768</NORD>
    <SARD>996,332</SARD>
    <SICI>2184,163</SICI>
    <SUD>2870,433</SUD>
  </Fabbisogno>
  <Fabbisogno>
    <Data>20180328</Data>
    <Mercato>MGP</Mercato>
    <Ora>18</Ora>
    <Italia>39655,066</Italia>
    <CNOR>4317,715</CNOR>
    <CSUD>6092,444</CSUD>
    <NORD>22759,163</NORD>
    <SARD>1063,529</SARD>
    <SICI>2306,68</SICI>
    <SUD>3115,535</SUD>
  </Fabbisogno>
  <Fabbisogno>
    <Data>20180328</Data>
    <Mercato>MGP</Mercato>
    <Ora>19</Ora>
    <Italia>41229,149</Italia>
    <CNOR>4459,571</CNOR>
    <CSUD>6548,137</CSUD>
    <NORD>23192,231</NORD>
    <SARD>1138,688</SARD>
    <SICI>2496,707</SICI>
    <SUD>3393,815</SUD>
  </Fabbisogno>
  <Fabbisogno>
    <Data>20180328</Data>
    <Mercato>MGP</Mercato>
    <Ora>20</Ora>
    <Italia>42296,814</Italia>
    <CNOR>4564,72</CNOR>
    <CSUD>6942,442</CSUD>
    <NORD>23366,832</NORD>
    <SARD>1200,375</SARD>
    <SICI>2652,724</SICI>
    <SUD>3569,721</SUD>
  </Fabbisogno>
  <Fabbisogno>
    <Data>20180328</Data>
    <Mercato>MGP</Mercato>
    <Ora>21</Ora>
    <Italia>41265,848</Italia>
    <CNOR>4343,6</CNOR>
    <CSUD>6738,003</CSUD>
    <NORD>22758,783</NORD>
    <SARD>1224,788</SARD>
    <SICI>2679,941</SICI>
    <SUD>3520,733</SUD>
  </Fabbisogno>
  <Fabbisogno>
    <Data>20180328</Data>
    <Mercato>MGP</Mercato>
    <Ora>22</Ora>
    <Italia>38225,209</Italia>
    <CNOR>4007,915</CNOR>
    <CSUD>6198,357</CSUD>
    <NORD>21131,965</NORD>
    <SARD>1142,526</SARD>
    <SICI>2508,821</SICI>
    <SUD>3235,625</SUD>
  </Fabbisogno>
  <Fabbisogno>
    <Data>20180328</Data>
    <Mercato>MGP</Mercato>
    <Ora>23</Ora>
    <Italia>34564,509</Italia>
    <CNOR>3631,937</CNOR>
    <CSUD>5577,241</CSUD>
    <NORD>19132,938</NORD>
    <SARD>1031,911</SARD>
    <SICI>2268,557</SICI>
    <SUD>2921,925</SUD>
  </Fabbisogno>
  <Fabbisogno>
    <Data>20180328</Data>
    <Mercato>MGP</Mercato>
    <Ora>24</Ora>
    <Italia>31105,822</Italia>
    <CNOR>3241,045</CNOR>
    <CSUD>4894,141</CSUD>
    <NORD>17464,422</NORD>
    <SARD>933,372</SARD>
    <SICI>2004,733</SICI>
    <SUD>2568,109</SUD>
  </Fabbisogno>
</NewDataSet>