<?xml version="1.0" standalone="yes"?>
<NewDataSet>
  <xs:schema id="NewDataSet" xmlns="" xmlns:xs="http://www.w3.org/2001/XMLSchema" xmlns:msdata="urn:schemas-microsoft-com:xml-msdata">
    <xs:element name="NewDataSet" msdata:IsDataSet="true" msdata:UseCurrentLocale="true">
      <xs:complexType>
        <xs:choice minOccurs="0" maxOccurs="unbounded">
          <xs:element name="Fabbisogno">
            <xs:complexType>
              <xs:sequence>
                <xs:element name="Data" type="xs:string" minOccurs="0" />
                <xs:element name="Mercato" type="xs:string" minOccurs="0" />
                <xs:element name="Ora" type="xs:string" minOccurs="0" />
                <xs:element name="Italia" type="xs:string" minOccurs="0" />
                <xs:element name="CNOR" type="xs:string" minOccurs="0" />
                <xs:element name="CSUD" type="xs:string" minOccurs="0" />
                <xs:element name="NORD" type="xs:string" minOccurs="0" />
                <xs:element name="SARD" type="xs:string" minOccurs="0" />
                <xs:element name="SICI" type="xs:string" minOccurs="0" />
                <xs:element name="SUD" type="xs:string" minOccurs="0" />
              </xs:sequence>
            </xs:complexType>
          </xs:element>
        </xs:choice>
      </xs:complexType>
    </xs:element>
  </xs:schema>
  <Fabbisogno>
    <Data>20181016</Data>
    <Mercato>MGP</Mercato>
    <Ora>1</Ora>
    <Italia>27655,728</Italia>
    <CNOR>2848,637</CNOR>
    <CSUD>4264,729</CSUD>
    <NORD>15816,455</NORD>
    <SARD>872,461</SARD>
    <SICI>1662,479</SICI>
    <SUD>2190,967</SUD>
  </Fabbisogno>
  <Fabbisogno>
    <Data>20181016</Data>
    <Mercato>MGP</Mercato>
    <Ora>2</Ora>
    <Italia>26266,451</Italia>
    <CNOR>2728,372</CNOR>
    <CSUD>3955,704</CSUD>
    <NORD>15154,559</NORD>
    <SARD>832,525</SARD>
    <SICI>1544,317</SICI>
    <SUD>2050,974</SUD>
  </Fabbisogno>
  <Fabbisogno>
    <Data>20181016</Data>
    <Mercato>MGP</Mercato>
    <Ora>3</Ora>
    <Italia>25386,541</Italia>
    <CNOR>2593,088</CNOR>
    <CSUD>3793,785</CSUD>
    <NORD>14709,953</NORD>
    <SARD>815,369</SARD>
    <SICI>1489,791</SICI>
    <SUD>1984,555</SUD>
  </Fabbisogno>
  <Fabbisogno>
    <Data>20181016</Data>
    <Mercato>MGP</Mercato>
    <Ora>4</Ora>
    <Italia>25242,348</Italia>
    <CNOR>2581,191</CNOR>
    <CSUD>3727,643</CSUD>
    <NORD>14691,556</NORD>
    <SARD>810,32</SARD>
    <SICI>1473,808</SICI>
    <SUD>1957,83</SUD>
  </Fabbisogno>
  <Fabbisogno>
    <Data>20181016</Data>
    <Mercato>MGP</Mercato>
    <Ora>5</Ora>
    <Italia>25231,986</Italia>
    <CNOR>2608,466</CNOR>
    <CSUD>3725,027</CSUD>
    <NORD>14676,102</NORD>
    <SARD>814,915</SARD>
    <SICI>1478,763</SICI>
    <SUD>1928,713</SUD>
  </Fabbisogno>
  <Fabbisogno>
    <Data>20181016</Data>
    <Mercato>MGP</Mercato>
    <Ora>6</Ora>
    <Italia>26625,385</Italia>
    <CNOR>2729,481</CNOR>
    <CSUD>3935,539</CSUD>
    <NORD>15562,8</NORD>
    <SARD>841,798</SARD>
    <SICI>1544,04</SICI>
    <SUD>2011,727</SUD>
  </Fabbisogno>
  <Fabbisogno>
    <Data>20181016</Data>
    <Mercato>MGP</Mercato>
    <Ora>7</Ora>
    <Italia>31204,237</Italia>
    <CNOR>3199,125</CNOR>
    <CSUD>4560,075</CSUD>
    <NORD>18494,891</NORD>
    <SARD>927,28</SARD>
    <SICI>1731,312</SICI>
    <SUD>2291,554</SUD>
  </Fabbisogno>
  <Fabbisogno>
    <Data>20181016</Data>
    <Mercato>MGP</Mercato>
    <Ora>8</Ora>
    <Italia>36546,413</Italia>
    <CNOR>3845,908</CNOR>
    <CSUD>5254,845</CSUD>
    <NORD>21787,996</NORD>
    <SARD>1071,676</SARD>
    <SICI>1967,609</SICI>
    <SUD>2618,379</SUD>
  </Fabbisogno>
  <Fabbisogno>
    <Data>20181016</Data>
    <Mercato>MGP</Mercato>
    <Ora>9</Ora>
    <Italia>40213,34</Italia>
    <CNOR>4316,216</CNOR>
    <CSUD>5732,117</CSUD>
    <NORD>23973,834</NORD>
    <SARD>1139,733</SARD>
    <SICI>2143,934</SICI>
    <SUD>2907,506</SUD>
  </Fabbisogno>
  <Fabbisogno>
    <Data>20181016</Data>
    <Mercato>MGP</Mercato>
    <Ora>10</Ora>
    <Italia>40773,787</Italia>
    <CNOR>4384,615</CNOR>
    <CSUD>5909,123</CSUD>
    <NORD>24329,729</NORD>
    <SARD>1107,104</SARD>
    <SICI>2169,85</SICI>
    <SUD>2873,366</SUD>
  </Fabbisogno>
  <Fabbisogno>
    <Data>20181016</Data>
    <Mercato>MGP</Mercato>
    <Ora>11</Ora>
    <Italia>40265,413</Italia>
    <CNOR>4372,195</CNOR>
    <CSUD>5876,872</CSUD>
    <NORD>24127,904</NORD>
    <SARD>1076,51</SARD>
    <SICI>2097,928</SICI>
    <SUD>2714,004</SUD>
  </Fabbisogno>
  <Fabbisogno>
    <Data>20181016</Data>
    <Mercato>MGP</Mercato>
    <Ora>12</Ora>
    <Italia>39846,267</Italia>
    <CNOR>4376,769</CNOR>
    <CSUD>5816,929</CSUD>
    <NORD>23891,336</NORD>
    <SARD>1057,385</SARD>
    <SICI>2064,088</SICI>
    <SUD>2639,76</SUD>
  </Fabbisogno>
  <Fabbisogno>
    <Data>20181016</Data>
    <Mercato>MGP</Mercato>
    <Ora>13</Ora>
    <Italia>37609,161</Italia>
    <CNOR>4083,353</CNOR>
    <CSUD>5756,468</CSUD>
    <NORD>22055,464</NORD>
    <SARD>1041,317</SARD>
    <SICI>2039,34</SICI>
    <SUD>2633,219</SUD>
  </Fabbisogno>
  <Fabbisogno>
    <Data>20181016</Data>
    <Mercato>MGP</Mercato>
    <Ora>14</Ora>
    <Italia>37590,071</Italia>
    <CNOR>3969,749</CNOR>
    <CSUD>5591,205</CSUD>
    <NORD>22516,792</NORD>
    <SARD>1002,099</SARD>
    <SICI>1977,956</SICI>
    <SUD>2532,27</SUD>
  </Fabbisogno>
  <Fabbisogno>
    <Data>20181016</Data>
    <Mercato>MGP</Mercato>
    <Ora>15</Ora>
    <Italia>38653,331</Italia>
    <CNOR>4185,247</CNOR>
    <CSUD>5692,192</CSUD>
    <NORD>23254,939</NORD>
    <SARD>992,505</SARD>
    <SICI>1979,47</SICI>
    <SUD>2548,978</SUD>
  </Fabbisogno>
  <Fabbisogno>
    <Data>20181016</Data>
    <Mercato>MGP</Mercato>
    <Ora>16</Ora>
    <Italia>39129,811</Italia>
    <CNOR>4234,349</CNOR>
    <CSUD>5766,857</CSUD>
    <NORD>23487,903</NORD>
    <SARD>1001,177</SARD>
    <SICI>2016,1</SICI>
    <SUD>2623,425</SUD>
  </Fabbisogno>
  <Fabbisogno>
    <Data>20181016</Data>
    <Mercato>MGP</Mercato>
    <Ora>17</Ora>
    <Italia>39576,942</Italia>
    <CNOR>4280,707</CNOR>
    <CSUD>5896,453</CSUD>
    <NORD>23511,122</NORD>
    <SARD>1023,19</SARD>
    <SICI>2099,232</SICI>
    <SUD>2766,238</SUD>
  </Fabbisogno>
  <Fabbisogno>
    <Data>20181016</Data>
    <Mercato>MGP</Mercato>
    <Ora>18</Ora>
    <Italia>39579,575</Italia>
    <CNOR>4259,471</CNOR>
    <CSUD>5991,234</CSUD>
    <NORD>23091,002</NORD>
    <SARD>1072,548</SARD>
    <SICI>2183,076</SICI>
    <SUD>2982,244</SUD>
  </Fabbisogno>
  <Fabbisogno>
    <Data>20181016</Data>
    <Mercato>MGP</Mercato>
    <Ora>19</Ora>
    <Italia>40971,507</Italia>
    <CNOR>4385,502</CNOR>
    <CSUD>6342,245</CSUD>
    <NORD>23395,024</NORD>
    <SARD>1118,057</SARD>
    <SICI>2407,686</SICI>
    <SUD>3322,993</SUD>
  </Fabbisogno>
  <Fabbisogno>
    <Data>20181016</Data>
    <Mercato>MGP</Mercato>
    <Ora>20</Ora>
    <Italia>42036,582</Italia>
    <CNOR>4460,98</CNOR>
    <CSUD>6655,722</CSUD>
    <NORD>23767,328</NORD>
    <SARD>1199,71</SARD>
    <SICI>2535,332</SICI>
    <SUD>3417,51</SUD>
  </Fabbisogno>
  <Fabbisogno>
    <Data>20181016</Data>
    <Mercato>MGP</Mercato>
    <Ora>21</Ora>
    <Italia>39924,741</Italia>
    <CNOR>4177,947</CNOR>
    <CSUD>6371,502</CSUD>
    <NORD>22462,824</NORD>
    <SARD>1167,513</SARD>
    <SICI>2457,036</SICI>
    <SUD>3287,919</SUD>
  </Fabbisogno>
  <Fabbisogno>
    <Data>20181016</Data>
    <Mercato>MGP</Mercato>
    <Ora>22</Ora>
    <Italia>37006,061</Italia>
    <CNOR>3895,947</CNOR>
    <CSUD>5849,09</CSUD>
    <NORD>20936,643</NORD>
    <SARD>1079,866</SARD>
    <SICI>2260,316</SICI>
    <SUD>2984,199</SUD>
  </Fabbisogno>
  <Fabbisogno>
    <Data>20181016</Data>
    <Mercato>MGP</Mercato>
    <Ora>23</Ora>
    <Italia>33583,95</Italia>
    <CNOR>3528,816</CNOR>
    <CSUD>5293,125</CSUD>
    <NORD>18985,026</NORD>
    <SARD>1004,904</SARD>
    <SICI>2077,812</SICI>
    <SUD>2694,267</SUD>
  </Fabbisogno>
  <Fabbisogno>
    <Data>20181016</Data>
    <Mercato>MGP</Mercato>
    <Ora>24</Ora>
    <Italia>30122,37</Italia>
    <CNOR>3114,609</CNOR>
    <CSUD>4683,546</CSUD>
    <NORD>17229,377</NORD>
    <SARD>925,618</SARD>
    <SICI>1812,72</SICI>
    <SUD>2356,5</SUD>
  </Fabbisogno>
</NewDataSet>