<?xml version="1.0" standalone="yes"?>
<NewDataSet>
  <xs:schema id="NewDataSet" xmlns="" xmlns:xs="http://www.w3.org/2001/XMLSchema" xmlns:msdata="urn:schemas-microsoft-com:xml-msdata">
    <xs:element name="NewDataSet" msdata:IsDataSet="true" msdata:UseCurrentLocale="true">
      <xs:complexType>
        <xs:choice minOccurs="0" maxOccurs="unbounded">
          <xs:element name="Fabbisogno">
            <xs:complexType>
              <xs:sequence>
                <xs:element name="Data" type="xs:string" minOccurs="0" />
                <xs:element name="Mercato" type="xs:string" minOccurs="0" />
                <xs:element name="Ora" type="xs:string" minOccurs="0" />
                <xs:element name="Italia" type="xs:string" minOccurs="0" />
                <xs:element name="CNOR" type="xs:string" minOccurs="0" />
                <xs:element name="CSUD" type="xs:string" minOccurs="0" />
                <xs:element name="NORD" type="xs:string" minOccurs="0" />
                <xs:element name="SARD" type="xs:string" minOccurs="0" />
                <xs:element name="SICI" type="xs:string" minOccurs="0" />
                <xs:element name="SUD" type="xs:string" minOccurs="0" />
              </xs:sequence>
            </xs:complexType>
          </xs:element>
        </xs:choice>
      </xs:complexType>
    </xs:element>
  </xs:schema>
  <Fabbisogno>
    <Data>20191002</Data>
    <Mercato>MGP</Mercato>
    <Ora>1</Ora>
    <Italia>27577,982</Italia>
    <CNOR>2958,982</CNOR>
    <CSUD>4222,28</CSUD>
    <NORD>15562,548</NORD>
    <SARD>880,011</SARD>
    <SICI>1668,297</SICI>
    <SUD>2285,864</SUD>
  </Fabbisogno>
  <Fabbisogno>
    <Data>20191002</Data>
    <Mercato>MGP</Mercato>
    <Ora>2</Ora>
    <Italia>26262,353</Italia>
    <CNOR>2841,484</CNOR>
    <CSUD>3962,79</CSUD>
    <NORD>14875,499</NORD>
    <SARD>842,405</SARD>
    <SICI>1561,152</SICI>
    <SUD>2179,023</SUD>
  </Fabbisogno>
  <Fabbisogno>
    <Data>20191002</Data>
    <Mercato>MGP</Mercato>
    <Ora>3</Ora>
    <Italia>25493,594</Italia>
    <CNOR>2763,775</CNOR>
    <CSUD>3840,798</CSUD>
    <NORD>14421,639</NORD>
    <SARD>825,897</SARD>
    <SICI>1508,316</SICI>
    <SUD>2133,169</SUD>
  </Fabbisogno>
  <Fabbisogno>
    <Data>20191002</Data>
    <Mercato>MGP</Mercato>
    <Ora>4</Ora>
    <Italia>25188,94</Italia>
    <CNOR>2737,795</CNOR>
    <CSUD>3747,334</CSUD>
    <NORD>14287,287</NORD>
    <SARD>815,062</SARD>
    <SICI>1491,606</SICI>
    <SUD>2109,856</SUD>
  </Fabbisogno>
  <Fabbisogno>
    <Data>20191002</Data>
    <Mercato>MGP</Mercato>
    <Ora>5</Ora>
    <Italia>25615,099</Italia>
    <CNOR>2765,168</CNOR>
    <CSUD>3788,059</CSUD>
    <NORD>14632,311</NORD>
    <SARD>818,726</SARD>
    <SICI>1491,783</SICI>
    <SUD>2119,052</SUD>
  </Fabbisogno>
  <Fabbisogno>
    <Data>20191002</Data>
    <Mercato>MGP</Mercato>
    <Ora>6</Ora>
    <Italia>26705,963</Italia>
    <CNOR>2883,249</CNOR>
    <CSUD>3932,205</CSUD>
    <NORD>15315,05</NORD>
    <SARD>844,343</SARD>
    <SICI>1542,584</SICI>
    <SUD>2188,532</SUD>
  </Fabbisogno>
  <Fabbisogno>
    <Data>20191002</Data>
    <Mercato>MGP</Mercato>
    <Ora>7</Ora>
    <Italia>31504,534</Italia>
    <CNOR>3343,972</CNOR>
    <CSUD>4612,33</CSUD>
    <NORD>18498,564</NORD>
    <SARD>924,623</SARD>
    <SICI>1694,002</SICI>
    <SUD>2431,043</SUD>
  </Fabbisogno>
  <Fabbisogno>
    <Data>20191002</Data>
    <Mercato>MGP</Mercato>
    <Ora>8</Ora>
    <Italia>35968,941</Italia>
    <CNOR>3816,043</CNOR>
    <CSUD>5189,628</CSUD>
    <NORD>21321,423</NORD>
    <SARD>1027,091</SARD>
    <SICI>1902,403</SICI>
    <SUD>2712,353</SUD>
  </Fabbisogno>
  <Fabbisogno>
    <Data>20191002</Data>
    <Mercato>MGP</Mercato>
    <Ora>9</Ora>
    <Italia>39696,566</Italia>
    <CNOR>4261,294</CNOR>
    <CSUD>5718,857</CSUD>
    <NORD>23616,719</NORD>
    <SARD>1095,351</SARD>
    <SICI>2069,746</SICI>
    <SUD>2934,599</SUD>
  </Fabbisogno>
  <Fabbisogno>
    <Data>20191002</Data>
    <Mercato>MGP</Mercato>
    <Ora>10</Ora>
    <Italia>40125,23</Italia>
    <CNOR>4350,627</CNOR>
    <CSUD>5902,334</CSUD>
    <NORD>23721,064</NORD>
    <SARD>1085,902</SARD>
    <SICI>2152,942</SICI>
    <SUD>2912,361</SUD>
  </Fabbisogno>
  <Fabbisogno>
    <Data>20191002</Data>
    <Mercato>MGP</Mercato>
    <Ora>11</Ora>
    <Italia>39910,383</Italia>
    <CNOR>4393,886</CNOR>
    <CSUD>5931,318</CSUD>
    <NORD>23516,718</NORD>
    <SARD>1058,94</SARD>
    <SICI>2123,022</SICI>
    <SUD>2886,499</SUD>
  </Fabbisogno>
  <Fabbisogno>
    <Data>20191002</Data>
    <Mercato>MGP</Mercato>
    <Ora>12</Ora>
    <Italia>39524,59</Italia>
    <CNOR>4323,83</CNOR>
    <CSUD>5870,56</CSUD>
    <NORD>23329,72</NORD>
    <SARD>1037,538</SARD>
    <SICI>2110,56</SICI>
    <SUD>2852,382</SUD>
  </Fabbisogno>
  <Fabbisogno>
    <Data>20191002</Data>
    <Mercato>MGP</Mercato>
    <Ora>13</Ora>
    <Italia>37587,073</Italia>
    <CNOR>4095,674</CNOR>
    <CSUD>5798,722</CSUD>
    <NORD>21709,548</NORD>
    <SARD>1028,263</SARD>
    <SICI>2106,524</SICI>
    <SUD>2848,342</SUD>
  </Fabbisogno>
  <Fabbisogno>
    <Data>20191002</Data>
    <Mercato>MGP</Mercato>
    <Ora>14</Ora>
    <Italia>37388,61</Italia>
    <CNOR>3981,485</CNOR>
    <CSUD>5607,457</CSUD>
    <NORD>21993,203</NORD>
    <SARD>992,408</SARD>
    <SICI>2046,578</SICI>
    <SUD>2767,479</SUD>
  </Fabbisogno>
  <Fabbisogno>
    <Data>20191002</Data>
    <Mercato>MGP</Mercato>
    <Ora>15</Ora>
    <Italia>38405,422</Italia>
    <CNOR>4185,121</CNOR>
    <CSUD>5739,098</CSUD>
    <NORD>22716,186</NORD>
    <SARD>982,545</SARD>
    <SICI>2034,087</SICI>
    <SUD>2748,385</SUD>
  </Fabbisogno>
  <Fabbisogno>
    <Data>20191002</Data>
    <Mercato>MGP</Mercato>
    <Ora>16</Ora>
    <Italia>38867,852</Italia>
    <CNOR>4263,072</CNOR>
    <CSUD>5836,617</CSUD>
    <NORD>22866,268</NORD>
    <SARD>993,092</SARD>
    <SICI>2087,177</SICI>
    <SUD>2821,626</SUD>
  </Fabbisogno>
  <Fabbisogno>
    <Data>20191002</Data>
    <Mercato>MGP</Mercato>
    <Ora>17</Ora>
    <Italia>39302,004</Italia>
    <CNOR>4312,318</CNOR>
    <CSUD>5908,35</CSUD>
    <NORD>22945,27</NORD>
    <SARD>1015,717</SARD>
    <SICI>2177,12</SICI>
    <SUD>2943,229</SUD>
  </Fabbisogno>
  <Fabbisogno>
    <Data>20191002</Data>
    <Mercato>MGP</Mercato>
    <Ora>18</Ora>
    <Italia>39320,809</Italia>
    <CNOR>4293,935</CNOR>
    <CSUD>5997,481</CSUD>
    <NORD>22592,553</NORD>
    <SARD>1067,383</SARD>
    <SICI>2261,844</SICI>
    <SUD>3107,613</SUD>
  </Fabbisogno>
  <Fabbisogno>
    <Data>20191002</Data>
    <Mercato>MGP</Mercato>
    <Ora>19</Ora>
    <Italia>40094,773</Italia>
    <CNOR>4346,623</CNOR>
    <CSUD>6235,92</CSUD>
    <NORD>22723,656</NORD>
    <SARD>1119,856</SARD>
    <SICI>2360,18</SICI>
    <SUD>3308,538</SUD>
  </Fabbisogno>
  <Fabbisogno>
    <Data>20191002</Data>
    <Mercato>MGP</Mercato>
    <Ora>20</Ora>
    <Italia>41573,553</Italia>
    <CNOR>4544,724</CNOR>
    <CSUD>6697,023</CSUD>
    <NORD>23149,63</NORD>
    <SARD>1191,546</SARD>
    <SICI>2510,398</SICI>
    <SUD>3480,232</SUD>
  </Fabbisogno>
  <Fabbisogno>
    <Data>20191002</Data>
    <Mercato>MGP</Mercato>
    <Ora>21</Ora>
    <Italia>39259,113</Italia>
    <CNOR>4233,03</CNOR>
    <CSUD>6333,013</CSUD>
    <NORD>21690,021</NORD>
    <SARD>1184,644</SARD>
    <SICI>2433,72</SICI>
    <SUD>3384,685</SUD>
  </Fabbisogno>
  <Fabbisogno>
    <Data>20191002</Data>
    <Mercato>MGP</Mercato>
    <Ora>22</Ora>
    <Italia>36200,216</Italia>
    <CNOR>3888,978</CNOR>
    <CSUD>5845,366</CSUD>
    <NORD>20027,611</NORD>
    <SARD>1108,222</SARD>
    <SICI>2262,21</SICI>
    <SUD>3067,829</SUD>
  </Fabbisogno>
  <Fabbisogno>
    <Data>20191002</Data>
    <Mercato>MGP</Mercato>
    <Ora>23</Ora>
    <Italia>32713,438</Italia>
    <CNOR>3428,323</CNOR>
    <CSUD>5300,582</CSUD>
    <NORD>18068,952</NORD>
    <SARD>1030,519</SARD>
    <SICI>2095,816</SICI>
    <SUD>2789,246</SUD>
  </Fabbisogno>
  <Fabbisogno>
    <Data>20191002</Data>
    <Mercato>MGP</Mercato>
    <Ora>24</Ora>
    <Italia>29567,831</Italia>
    <CNOR>3086,322</CNOR>
    <CSUD>4659,905</CSUD>
    <NORD>16520,364</NORD>
    <SARD>944,945</SARD>
    <SICI>1873,142</SICI>
    <SUD>2483,153</SUD>
  </Fabbisogno>
</NewDataSet>