<?xml version="1.0" standalone="yes"?>
<NewDataSet>
  <xs:schema id="NewDataSet" xmlns="" xmlns:xs="http://www.w3.org/2001/XMLSchema" xmlns:msdata="urn:schemas-microsoft-com:xml-msdata">
    <xs:element name="NewDataSet" msdata:IsDataSet="true" msdata:UseCurrentLocale="true">
      <xs:complexType>
        <xs:choice minOccurs="0" maxOccurs="unbounded">
          <xs:element name="Fabbisogno">
            <xs:complexType>
              <xs:sequence>
                <xs:element name="Data" type="xs:string" minOccurs="0" />
                <xs:element name="Mercato" type="xs:string" minOccurs="0" />
                <xs:element name="Ora" type="xs:string" minOccurs="0" />
                <xs:element name="Italia" type="xs:string" minOccurs="0" />
                <xs:element name="CALA" type="xs:string" minOccurs="0" />
                <xs:element name="CNOR" type="xs:string" minOccurs="0" />
                <xs:element name="CSUD" type="xs:string" minOccurs="0" />
                <xs:element name="NORD" type="xs:string" minOccurs="0" />
                <xs:element name="SARD" type="xs:string" minOccurs="0" />
                <xs:element name="SICI" type="xs:string" minOccurs="0" />
                <xs:element name="SUD" type="xs:string" minOccurs="0" />
              </xs:sequence>
            </xs:complexType>
          </xs:element>
        </xs:choice>
      </xs:complexType>
    </xs:element>
  </xs:schema>
  <Fabbisogno>
    <Data>20210618</Data>
    <Mercato>MGP</Mercato>
    <Ora>1</Ora>
    <Italia>30217,669</Italia>
    <CALA>551,288</CALA>
    <CNOR>2449,067</CNOR>
    <CSUD>5175,833</CSUD>
    <NORD>17494,341</NORD>
    <SARD>998,953</SARD>
    <SICI>1660,278</SICI>
    <SUD>1887,909</SUD>
  </Fabbisogno>
  <Fabbisogno>
    <Data>20210618</Data>
    <Mercato>MGP</Mercato>
    <Ora>2</Ora>
    <Italia>28679,269</Italia>
    <CALA>509,078</CALA>
    <CNOR>2307,39</CNOR>
    <CSUD>4831,966</CSUD>
    <NORD>16750,327</NORD>
    <SARD>954,791</SARD>
    <SICI>1537,207</SICI>
    <SUD>1788,51</SUD>
  </Fabbisogno>
  <Fabbisogno>
    <Data>20210618</Data>
    <Mercato>MGP</Mercato>
    <Ora>3</Ora>
    <Italia>27959,985</Italia>
    <CALA>490,368</CALA>
    <CNOR>2248,998</CNOR>
    <CSUD>4648,05</CSUD>
    <NORD>16396,571</NORD>
    <SARD>928,604</SARD>
    <SICI>1477,6</SICI>
    <SUD>1769,794</SUD>
  </Fabbisogno>
  <Fabbisogno>
    <Data>20210618</Data>
    <Mercato>MGP</Mercato>
    <Ora>4</Ora>
    <Italia>27481,28</Italia>
    <CALA>482,934</CALA>
    <CNOR>2213,415</CNOR>
    <CSUD>4576,266</CSUD>
    <NORD>16142,819</NORD>
    <SARD>913,418000000001</SARD>
    <SICI>1454,297</SICI>
    <SUD>1698,131</SUD>
  </Fabbisogno>
  <Fabbisogno>
    <Data>20210618</Data>
    <Mercato>MGP</Mercato>
    <Ora>5</Ora>
    <Italia>27491,47</Italia>
    <CALA>488,435</CALA>
    <CNOR>2198,138</CNOR>
    <CSUD>4557,527</CSUD>
    <NORD>16195,714</NORD>
    <SARD>912,058</SARD>
    <SICI>1458,231</SICI>
    <SUD>1681,367</SUD>
  </Fabbisogno>
  <Fabbisogno>
    <Data>20210618</Data>
    <Mercato>MGP</Mercato>
    <Ora>6</Ora>
    <Italia>27750,654</Italia>
    <CALA>480,202</CALA>
    <CNOR>2212,597</CNOR>
    <CSUD>4551,092</CSUD>
    <NORD>16517,681</NORD>
    <SARD>883,59</SARD>
    <SICI>1478,531</SICI>
    <SUD>1626,961</SUD>
  </Fabbisogno>
  <Fabbisogno>
    <Data>20210618</Data>
    <Mercato>MGP</Mercato>
    <Ora>7</Ora>
    <Italia>30943,042</Italia>
    <CALA>527,42</CALA>
    <CNOR>2534,679</CNOR>
    <CSUD>5052,468</CSUD>
    <NORD>18523,208</NORD>
    <SARD>954,303</SARD>
    <SICI>1562,644</SICI>
    <SUD>1788,32</SUD>
  </Fabbisogno>
  <Fabbisogno>
    <Data>20210618</Data>
    <Mercato>MGP</Mercato>
    <Ora>8</Ora>
    <Italia>35784,762</Italia>
    <CALA>627,477</CALA>
    <CNOR>3009,58</CNOR>
    <CSUD>5817,846</CSUD>
    <NORD>21395,279</NORD>
    <SARD>1082,122</SARD>
    <SICI>1827,223</SICI>
    <SUD>2025,235</SUD>
  </Fabbisogno>
  <Fabbisogno>
    <Data>20210618</Data>
    <Mercato>MGP</Mercato>
    <Ora>9</Ora>
    <Italia>40474,133</Italia>
    <CALA>708,943</CALA>
    <CNOR>3509,432</CNOR>
    <CSUD>6562,751</CSUD>
    <NORD>24121,883</NORD>
    <SARD>1187,284</SARD>
    <SICI>2103,557</SICI>
    <SUD>2280,283</SUD>
  </Fabbisogno>
  <Fabbisogno>
    <Data>20210618</Data>
    <Mercato>MGP</Mercato>
    <Ora>10</Ora>
    <Italia>41789,55</Italia>
    <CALA>728,173</CALA>
    <CNOR>3690,272</CNOR>
    <CSUD>6965,504</CSUD>
    <NORD>24716,335</NORD>
    <SARD>1191,665</SARD>
    <SICI>2189,429</SICI>
    <SUD>2308,172</SUD>
  </Fabbisogno>
  <Fabbisogno>
    <Data>20210618</Data>
    <Mercato>MGP</Mercato>
    <Ora>11</Ora>
    <Italia>41955,737</Italia>
    <CALA>708,27</CALA>
    <CNOR>3733,922</CNOR>
    <CSUD>7049,827</CSUD>
    <NORD>24830,92</NORD>
    <SARD>1150,526</SARD>
    <SICI>2186,079</SICI>
    <SUD>2296,193</SUD>
  </Fabbisogno>
  <Fabbisogno>
    <Data>20210618</Data>
    <Mercato>MGP</Mercato>
    <Ora>12</Ora>
    <Italia>41898,97</Italia>
    <CALA>697,455</CALA>
    <CNOR>3753,984</CNOR>
    <CSUD>7042,901</CSUD>
    <NORD>24813,047</NORD>
    <SARD>1125,047</SARD>
    <SICI>2162,926</SICI>
    <SUD>2303,61</SUD>
  </Fabbisogno>
  <Fabbisogno>
    <Data>20210618</Data>
    <Mercato>MGP</Mercato>
    <Ora>13</Ora>
    <Italia>40652,425</Italia>
    <CALA>690,976999999999</CALA>
    <CNOR>3571,417</CNOR>
    <CSUD>7037,683</CSUD>
    <NORD>23760,724</NORD>
    <SARD>1130,05</SARD>
    <SICI>2148,851</SICI>
    <SUD>2312,723</SUD>
  </Fabbisogno>
  <Fabbisogno>
    <Data>20210618</Data>
    <Mercato>MGP</Mercato>
    <Ora>14</Ora>
    <Italia>40600,996</Italia>
    <CALA>672,713</CALA>
    <CNOR>3486,028</CNOR>
    <CSUD>6874,122</CSUD>
    <NORD>24118,876</NORD>
    <SARD>1114,412</SARD>
    <SICI>2095,718</SICI>
    <SUD>2239,127</SUD>
  </Fabbisogno>
  <Fabbisogno>
    <Data>20210618</Data>
    <Mercato>MGP</Mercato>
    <Ora>15</Ora>
    <Italia>41149,028</Italia>
    <CALA>679,245</CALA>
    <CNOR>3600,62</CNOR>
    <CSUD>6925,246</CSUD>
    <NORD>24546,757</NORD>
    <SARD>1097,361</SARD>
    <SICI>2076,059</SICI>
    <SUD>2223,74</SUD>
  </Fabbisogno>
  <Fabbisogno>
    <Data>20210618</Data>
    <Mercato>MGP</Mercato>
    <Ora>16</Ora>
    <Italia>41355,482</Italia>
    <CALA>688,308</CALA>
    <CNOR>3659,245</CNOR>
    <CSUD>6969,083</CSUD>
    <NORD>24631,25</NORD>
    <SARD>1095,852</SARD>
    <SICI>2071,507</SICI>
    <SUD>2240,237</SUD>
  </Fabbisogno>
  <Fabbisogno>
    <Data>20210618</Data>
    <Mercato>MGP</Mercato>
    <Ora>17</Ora>
    <Italia>41821,668</Italia>
    <CALA>712,991999999999</CALA>
    <CNOR>3724,697</CNOR>
    <CSUD>7039,373</CSUD>
    <NORD>24769,046</NORD>
    <SARD>1124,746</SARD>
    <SICI>2135,9</SICI>
    <SUD>2314,914</SUD>
  </Fabbisogno>
  <Fabbisogno>
    <Data>20210618</Data>
    <Mercato>MGP</Mercato>
    <Ora>18</Ora>
    <Italia>41472,024</Italia>
    <CALA>740,290999999999</CALA>
    <CNOR>3635,593</CNOR>
    <CSUD>7042,285</CSUD>
    <NORD>24293,705</NORD>
    <SARD>1161,717</SARD>
    <SICI>2194,163</SICI>
    <SUD>2404,27</SUD>
  </Fabbisogno>
  <Fabbisogno>
    <Data>20210618</Data>
    <Mercato>MGP</Mercato>
    <Ora>19</Ora>
    <Italia>41183,403</Italia>
    <CALA>761,228999999999</CALA>
    <CNOR>3553,739</CNOR>
    <CSUD>7058,201</CSUD>
    <NORD>23877,761</NORD>
    <SARD>1224,541</SARD>
    <SICI>2233,846</SICI>
    <SUD>2474,086</SUD>
  </Fabbisogno>
  <Fabbisogno>
    <Data>20210618</Data>
    <Mercato>MGP</Mercato>
    <Ora>20</Ora>
    <Italia>40300,369</Italia>
    <CALA>758,17</CALA>
    <CNOR>3491,86</CNOR>
    <CSUD>6958,825</CSUD>
    <NORD>23207,991</NORD>
    <SARD>1208,732</SARD>
    <SICI>2233,279</SICI>
    <SUD>2441,512</SUD>
  </Fabbisogno>
  <Fabbisogno>
    <Data>20210618</Data>
    <Mercato>MGP</Mercato>
    <Ora>21</Ora>
    <Italia>39647,229</Italia>
    <CALA>814,682999999999</CALA>
    <CNOR>3366,372</CNOR>
    <CSUD>6899,773</CSUD>
    <NORD>22464,506</NORD>
    <SARD>1246,495</SARD>
    <SICI>2316,219</SICI>
    <SUD>2539,181</SUD>
  </Fabbisogno>
  <Fabbisogno>
    <Data>20210618</Data>
    <Mercato>MGP</Mercato>
    <Ora>22</Ora>
    <Italia>38709,511</Italia>
    <CALA>790,226</CALA>
    <CNOR>3281,155</CNOR>
    <CSUD>6788,463</CSUD>
    <NORD>21900,401</NORD>
    <SARD>1241,546</SARD>
    <SICI>2255,679</SICI>
    <SUD>2452,041</SUD>
  </Fabbisogno>
  <Fabbisogno>
    <Data>20210618</Data>
    <Mercato>MGP</Mercato>
    <Ora>23</Ora>
    <Italia>35917,327</Italia>
    <CALA>722,058999999999</CALA>
    <CNOR>3007,755</CNOR>
    <CSUD>6289,622</CSUD>
    <NORD>20370,3</NORD>
    <SARD>1161,922</SARD>
    <SICI>2092,438</SICI>
    <SUD>2273,231</SUD>
  </Fabbisogno>
  <Fabbisogno>
    <Data>20210618</Data>
    <Mercato>MGP</Mercato>
    <Ora>24</Ora>
    <Italia>32802,463</Italia>
    <CALA>630,857</CALA>
    <CNOR>2643,171</CNOR>
    <CSUD>5725,063</CSUD>
    <NORD>18784,931</NORD>
    <SARD>1072,263</SARD>
    <SICI>1872,956</SICI>
    <SUD>2073,222</SUD>
  </Fabbisogno>
</NewDataSet>