<?xml version="1.0" standalone="yes"?>
<NewDataSet>
  <xs:schema id="NewDataSet" xmlns="" xmlns:xs="http://www.w3.org/2001/XMLSchema" xmlns:msdata="urn:schemas-microsoft-com:xml-msdata">
    <xs:element name="NewDataSet" msdata:IsDataSet="true" msdata:UseCurrentLocale="true">
      <xs:complexType>
        <xs:choice minOccurs="0" maxOccurs="unbounded">
          <xs:element name="Fabbisogno">
            <xs:complexType>
              <xs:sequence>
                <xs:element name="Data" type="xs:string" minOccurs="0" />
                <xs:element name="Mercato" type="xs:string" minOccurs="0" />
                <xs:element name="Ora" type="xs:string" minOccurs="0" />
                <xs:element name="Italia" type="xs:string" minOccurs="0" />
                <xs:element name="CALA" type="xs:string" minOccurs="0" />
                <xs:element name="CNOR" type="xs:string" minOccurs="0" />
                <xs:element name="CSUD" type="xs:string" minOccurs="0" />
                <xs:element name="NORD" type="xs:string" minOccurs="0" />
                <xs:element name="SARD" type="xs:string" minOccurs="0" />
                <xs:element name="SICI" type="xs:string" minOccurs="0" />
                <xs:element name="SUD" type="xs:string" minOccurs="0" />
              </xs:sequence>
            </xs:complexType>
          </xs:element>
        </xs:choice>
      </xs:complexType>
    </xs:element>
  </xs:schema>
  <Fabbisogno>
    <Data>20230404</Data>
    <Mercato>MGP</Mercato>
    <Ora>1</Ora>
    <Italia>26139,393</Italia>
    <CALA>475,234</CALA>
    <CNOR>2079,796</CNOR>
    <CSUD>4464,187</CSUD>
    <NORD>15118,628</NORD>
    <SARD>760,318</SARD>
    <SICI>1578,418</SICI>
    <SUD>1662,812</SUD>
  </Fabbisogno>
  <Fabbisogno>
    <Data>20230404</Data>
    <Mercato>MGP</Mercato>
    <Ora>2</Ora>
    <Italia>24834,602</Italia>
    <CALA>436,261</CALA>
    <CNOR>2022,894</CNOR>
    <CSUD>4164,831</CSUD>
    <NORD>14458,068</NORD>
    <SARD>713,605</SARD>
    <SICI>1466,739</SICI>
    <SUD>1572,204</SUD>
  </Fabbisogno>
  <Fabbisogno>
    <Data>20230404</Data>
    <Mercato>MGP</Mercato>
    <Ora>3</Ora>
    <Italia>24062,888</Italia>
    <CALA>416,201</CALA>
    <CNOR>1921,406</CNOR>
    <CSUD>3979,645</CSUD>
    <NORD>14148,222</NORD>
    <SARD>692,486</SARD>
    <SICI>1401,869</SICI>
    <SUD>1503,059</SUD>
  </Fabbisogno>
  <Fabbisogno>
    <Data>20230404</Data>
    <Mercato>MGP</Mercato>
    <Ora>4</Ora>
    <Italia>24054,137</Italia>
    <CALA>416,378</CALA>
    <CNOR>1916,212</CNOR>
    <CSUD>3996,118</CSUD>
    <NORD>14154,568</NORD>
    <SARD>692,53</SARD>
    <SICI>1386,716</SICI>
    <SUD>1491,615</SUD>
  </Fabbisogno>
  <Fabbisogno>
    <Data>20230404</Data>
    <Mercato>MGP</Mercato>
    <Ora>5</Ora>
    <Italia>24287,703</Italia>
    <CALA>419,333</CALA>
    <CNOR>1979,514</CNOR>
    <CSUD>4002,224</CSUD>
    <NORD>14278,116</NORD>
    <SARD>695,343</SARD>
    <SICI>1399,194</SICI>
    <SUD>1513,979</SUD>
  </Fabbisogno>
  <Fabbisogno>
    <Data>20230404</Data>
    <Mercato>MGP</Mercato>
    <Ora>6</Ora>
    <Italia>25926,218</Italia>
    <CALA>445,357</CALA>
    <CNOR>2043,112</CNOR>
    <CSUD>4302,719</CSUD>
    <NORD>15306,573</NORD>
    <SARD>739,864</SARD>
    <SICI>1479,451</SICI>
    <SUD>1609,142</SUD>
  </Fabbisogno>
  <Fabbisogno>
    <Data>20230404</Data>
    <Mercato>MGP</Mercato>
    <Ora>7</Ora>
    <Italia>30904,425</Italia>
    <CALA>507,974</CALA>
    <CNOR>2626,984</CNOR>
    <CSUD>5013,194</CSUD>
    <NORD>18439,606</NORD>
    <SARD>848,398</SARD>
    <SICI>1672,087</SICI>
    <SUD>1796,182</SUD>
  </Fabbisogno>
  <Fabbisogno>
    <Data>20230404</Data>
    <Mercato>MGP</Mercato>
    <Ora>8</Ora>
    <Italia>35926,544</Italia>
    <CALA>602,69</CALA>
    <CNOR>3186,131</CNOR>
    <CSUD>5819,898</CSUD>
    <NORD>21394,297</NORD>
    <SARD>966,922</SARD>
    <SICI>1919,569</SICI>
    <SUD>2037,037</SUD>
  </Fabbisogno>
  <Fabbisogno>
    <Data>20230404</Data>
    <Mercato>MGP</Mercato>
    <Ora>9</Ora>
    <Italia>39281,373</Italia>
    <CALA>656,177</CALA>
    <CNOR>3630,98</CNOR>
    <CSUD>6323,395</CSUD>
    <NORD>23376,738</NORD>
    <SARD>1041,053</SARD>
    <SICI>2051,675</SICI>
    <SUD>2201,355</SUD>
  </Fabbisogno>
  <Fabbisogno>
    <Data>20230404</Data>
    <Mercato>MGP</Mercato>
    <Ora>10</Ora>
    <Italia>39253,809</Italia>
    <CALA>659,567</CALA>
    <CNOR>3581,111</CNOR>
    <CSUD>6432,018</CSUD>
    <NORD>23241,363</NORD>
    <SARD>1016,774</SARD>
    <SICI>2073,582</SICI>
    <SUD>2249,394</SUD>
  </Fabbisogno>
  <Fabbisogno>
    <Data>20230404</Data>
    <Mercato>MGP</Mercato>
    <Ora>11</Ora>
    <Italia>37805,318</Italia>
    <CALA>639,741</CALA>
    <CNOR>3382,806</CNOR>
    <CSUD>6306,096</CSUD>
    <NORD>22314,636</NORD>
    <SARD>960,24</SARD>
    <SICI>2005,279</SICI>
    <SUD>2196,52</SUD>
  </Fabbisogno>
  <Fabbisogno>
    <Data>20230404</Data>
    <Mercato>MGP</Mercato>
    <Ora>12</Ora>
    <Italia>37051,88</Italia>
    <CALA>631,4</CALA>
    <CNOR>3319,301</CNOR>
    <CSUD>6182,321</CSUD>
    <NORD>21836,75</NORD>
    <SARD>929,048</SARD>
    <SICI>1965,107</SICI>
    <SUD>2187,953</SUD>
  </Fabbisogno>
  <Fabbisogno>
    <Data>20230404</Data>
    <Mercato>MGP</Mercato>
    <Ora>13</Ora>
    <Italia>35553,239</Italia>
    <CALA>626,759</CALA>
    <CNOR>3073,012</CNOR>
    <CSUD>6191,202</CSUD>
    <NORD>20563,488</NORD>
    <SARD>926,493</SARD>
    <SICI>1944,891</SICI>
    <SUD>2227,394</SUD>
  </Fabbisogno>
  <Fabbisogno>
    <Data>20230404</Data>
    <Mercato>MGP</Mercato>
    <Ora>14</Ora>
    <Italia>35372,723</Italia>
    <CALA>612,35</CALA>
    <CNOR>3016,375</CNOR>
    <CSUD>6071,705</CSUD>
    <NORD>20672,841</NORD>
    <SARD>917,903</SARD>
    <SICI>1915,062</SICI>
    <SUD>2166,487</SUD>
  </Fabbisogno>
  <Fabbisogno>
    <Data>20230404</Data>
    <Mercato>MGP</Mercato>
    <Ora>15</Ora>
    <Italia>35946,952</Italia>
    <CALA>616,065</CALA>
    <CNOR>3144,516</CNOR>
    <CSUD>6155,185</CSUD>
    <NORD>21109,87</NORD>
    <SARD>897,084</SARD>
    <SICI>1906,302</SICI>
    <SUD>2117,93</SUD>
  </Fabbisogno>
  <Fabbisogno>
    <Data>20230404</Data>
    <Mercato>MGP</Mercato>
    <Ora>16</Ora>
    <Italia>35941,783</Italia>
    <CALA>611,877</CALA>
    <CNOR>3206,689</CNOR>
    <CSUD>6190,37</CSUD>
    <NORD>21033,5</NORD>
    <SARD>887,11</SARD>
    <SICI>1913,247</SICI>
    <SUD>2098,99</SUD>
  </Fabbisogno>
  <Fabbisogno>
    <Data>20230404</Data>
    <Mercato>MGP</Mercato>
    <Ora>17</Ora>
    <Italia>36013,242</Italia>
    <CALA>621,322</CALA>
    <CNOR>3202,532</CNOR>
    <CSUD>6144,936</CSUD>
    <NORD>21078,35</NORD>
    <SARD>901,659</SARD>
    <SICI>1931,637</SICI>
    <SUD>2132,806</SUD>
  </Fabbisogno>
  <Fabbisogno>
    <Data>20230404</Data>
    <Mercato>MGP</Mercato>
    <Ora>18</Ora>
    <Italia>35789,95</Italia>
    <CALA>641,431</CALA>
    <CNOR>3117,198</CNOR>
    <CSUD>6078,97</CSUD>
    <NORD>20800,798</NORD>
    <SARD>942,124</SARD>
    <SICI>2014,576</SICI>
    <SUD>2194,853</SUD>
  </Fabbisogno>
  <Fabbisogno>
    <Data>20230404</Data>
    <Mercato>MGP</Mercato>
    <Ora>19</Ora>
    <Italia>36288,431</Italia>
    <CALA>669,288</CALA>
    <CNOR>3103,212</CNOR>
    <CSUD>6360,621</CSUD>
    <NORD>20781,212</NORD>
    <SARD>997,323</SARD>
    <SICI>2101,293</SICI>
    <SUD>2275,482</SUD>
  </Fabbisogno>
  <Fabbisogno>
    <Data>20230404</Data>
    <Mercato>MGP</Mercato>
    <Ora>20</Ora>
    <Italia>37725,975</Italia>
    <CALA>744,096</CALA>
    <CNOR>3262,999</CNOR>
    <CSUD>6767,593</CSUD>
    <NORD>21232,95</NORD>
    <SARD>1044,234</SARD>
    <SICI>2269,451</SICI>
    <SUD>2404,652</SUD>
  </Fabbisogno>
  <Fabbisogno>
    <Data>20230404</Data>
    <Mercato>MGP</Mercato>
    <Ora>21</Ora>
    <Italia>37998,442</Italia>
    <CALA>762,363</CALA>
    <CNOR>3262,546</CNOR>
    <CSUD>6901,98</CSUD>
    <NORD>21068,947</NORD>
    <SARD>1108,095</SARD>
    <SICI>2399,451</SICI>
    <SUD>2495,06</SUD>
  </Fabbisogno>
  <Fabbisogno>
    <Data>20230404</Data>
    <Mercato>MGP</Mercato>
    <Ora>22</Ora>
    <Italia>35688,444</Italia>
    <CALA>726,485</CALA>
    <CNOR>2998,952</CNOR>
    <CSUD>6447,893</CSUD>
    <NORD>19877,369</NORD>
    <SARD>1063,785</SARD>
    <SICI>2251,669</SICI>
    <SUD>2322,291</SUD>
  </Fabbisogno>
  <Fabbisogno>
    <Data>20230404</Data>
    <Mercato>MGP</Mercato>
    <Ora>23</Ora>
    <Italia>32056,991</Italia>
    <CALA>649,354</CALA>
    <CNOR>2665,328</CNOR>
    <CSUD>5779,645</CSUD>
    <NORD>17857,1</NORD>
    <SARD>969,244</SARD>
    <SICI>2021,161</SICI>
    <SUD>2115,159</SUD>
  </Fabbisogno>
  <Fabbisogno>
    <Data>20230404</Data>
    <Mercato>MGP</Mercato>
    <Ora>24</Ora>
    <Italia>29002,283</Italia>
    <CALA>558,928</CALA>
    <CNOR>2340,863</CNOR>
    <CSUD>5136,226</CSUD>
    <NORD>16399,245</NORD>
    <SARD>869,322</SARD>
    <SICI>1794,212</SICI>
    <SUD>1903,487</SUD>
  </Fabbisogno>
</NewDataSet>