<?xml version="1.0" standalone="yes"?>
<NewDataSet>
  <xs:schema id="NewDataSet" xmlns="" xmlns:xs="http://www.w3.org/2001/XMLSchema" xmlns:msdata="urn:schemas-microsoft-com:xml-msdata">
    <xs:element name="NewDataSet" msdata:IsDataSet="true" msdata:UseCurrentLocale="true">
      <xs:complexType>
        <xs:choice minOccurs="0" maxOccurs="unbounded">
          <xs:element name="Prezzi">
            <xs:complexType>
              <xs:sequence>
                <xs:element name="Data" type="xs:string" minOccurs="0" />
                <xs:element name="Mercato" type="xs:string" minOccurs="0" />
                <xs:element name="Ora" type="xs:string" minOccurs="0" />
                <xs:element name="PUN" type="xs:string" minOccurs="0" />
                <xs:element name="NAT" type="xs:string" minOccurs="0" />
                <xs:element name="CNOR" type="xs:string" minOccurs="0" />
                <xs:element name="CSUD" type="xs:string" minOccurs="0" />
                <xs:element name="NORD" type="xs:string" minOccurs="0" />
                <xs:element name="SARD" type="xs:string" minOccurs="0" />
                <xs:element name="SICI" type="xs:string" minOccurs="0" />
                <xs:element name="SUD" type="xs:string" minOccurs="0" />
                <xs:element name="AUST" type="xs:string" minOccurs="0" />
                <xs:element name="BRNN" type="xs:string" minOccurs="0" />
                <xs:element name="COAC" type="xs:string" minOccurs="0" />
                <xs:element name="CORS" type="xs:string" minOccurs="0" />
                <xs:element name="FOGN" type="xs:string" minOccurs="0" />
                <xs:element name="FRAN" type="xs:string" minOccurs="0" />
                <xs:element name="GREC" type="xs:string" minOccurs="0" />
                <xs:element name="MFTV" type="xs:string" minOccurs="0" />
                <xs:element name="PRGP" type="xs:string" minOccurs="0" />
                <xs:element name="ROSN" type="xs:string" minOccurs="0" />
                <xs:element name="SLOV" type="xs:string" minOccurs="0" />
                <xs:element name="SVIZ" type="xs:string" minOccurs="0" />
                <xs:element name="BSP" type="xs:string" minOccurs="0" />
                <xs:element name="MALT" type="xs:string" minOccurs="0" />
                <xs:element name="XAUS" type="xs:string" minOccurs="0" />
                <xs:element name="XFRA" type="xs:string" minOccurs="0" />
              </xs:sequence>
            </xs:complexType>
          </xs:element>
        </xs:choice>
      </xs:complexType>
    </xs:element>
  </xs:schema>
  <Prezzi>
    <Data>20181107</Data>
    <Mercato>MGP</Mercato>
    <Ora>1</Ora>
    <PUN>54,280000</PUN>
    <NAT>54,280000</NAT>
    <CNOR>54,280000</CNOR>
    <CSUD>54,280000</CSUD>
    <NORD>54,280000</NORD>
    <SARD>54,280000</SARD>
    <SICI>54,280000</SICI>
    <SUD>54,280000</SUD>
    <AUST>54,280000</AUST>
    <BRNN>54,280000</BRNN>
    <COAC>54,280000</COAC>
    <CORS>54,280000</CORS>
    <FOGN>54,280000</FOGN>
    <FRAN>54,280000</FRAN>
    <GREC>54,280000</GREC>
    <MFTV>54,280000</MFTV>
    <PRGP>54,280000</PRGP>
    <ROSN>54,280000</ROSN>
    <SLOV>54,280000</SLOV>
    <SVIZ>54,280000</SVIZ>
    <BSP>54,280000</BSP>
    <MALT>54,280000</MALT>
    <XAUS>54,280000</XAUS>
    <XFRA>54,280000</XFRA>
  </Prezzi>
  <Prezzi>
    <Data>20181107</Data>
    <Mercato>MGP</Mercato>
    <Ora>2</Ora>
    <PUN>52,150000</PUN>
    <NAT>52,150000</NAT>
    <CNOR>52,150000</CNOR>
    <CSUD>52,150000</CSUD>
    <NORD>52,150000</NORD>
    <SARD>52,150000</SARD>
    <SICI>52,150000</SICI>
    <SUD>52,150000</SUD>
    <AUST>52,150000</AUST>
    <BRNN>52,150000</BRNN>
    <COAC>52,150000</COAC>
    <CORS>52,150000</CORS>
    <FOGN>52,150000</FOGN>
    <FRAN>52,150000</FRAN>
    <GREC>52,150000</GREC>
    <MFTV>52,150000</MFTV>
    <PRGP>52,150000</PRGP>
    <ROSN>52,150000</ROSN>
    <SLOV>52,150000</SLOV>
    <SVIZ>52,150000</SVIZ>
    <BSP>52,150000</BSP>
    <MALT>52,150000</MALT>
    <XAUS>52,150000</XAUS>
    <XFRA>52,150000</XFRA>
  </Prezzi>
  <Prezzi>
    <Data>20181107</Data>
    <Mercato>MGP</Mercato>
    <Ora>3</Ora>
    <PUN>52,150000</PUN>
    <NAT>52,150000</NAT>
    <CNOR>52,150000</CNOR>
    <CSUD>52,150000</CSUD>
    <NORD>52,150000</NORD>
    <SARD>52,150000</SARD>
    <SICI>52,150000</SICI>
    <SUD>52,150000</SUD>
    <AUST>52,150000</AUST>
    <BRNN>52,150000</BRNN>
    <COAC>52,150000</COAC>
    <CORS>52,150000</CORS>
    <FOGN>52,150000</FOGN>
    <FRAN>52,150000</FRAN>
    <GREC>52,150000</GREC>
    <MFTV>52,150000</MFTV>
    <PRGP>52,150000</PRGP>
    <ROSN>52,150000</ROSN>
    <SLOV>52,150000</SLOV>
    <SVIZ>52,150000</SVIZ>
    <BSP>52,150000</BSP>
    <MALT>52,150000</MALT>
    <XAUS>52,150000</XAUS>
    <XFRA>52,150000</XFRA>
  </Prezzi>
  <Prezzi>
    <Data>20181107</Data>
    <Mercato>MGP</Mercato>
    <Ora>4</Ora>
    <PUN>50,000000</PUN>
    <NAT>50,000000</NAT>
    <CNOR>50,000000</CNOR>
    <CSUD>50,000000</CSUD>
    <NORD>50,000000</NORD>
    <SARD>50,000000</SARD>
    <SICI>50,000000</SICI>
    <SUD>50,000000</SUD>
    <AUST>50,000000</AUST>
    <BRNN>50,000000</BRNN>
    <COAC>50,000000</COAC>
    <CORS>50,000000</CORS>
    <FOGN>50,000000</FOGN>
    <FRAN>50,000000</FRAN>
    <GREC>50,000000</GREC>
    <MFTV>50,000000</MFTV>
    <PRGP>50,000000</PRGP>
    <ROSN>50,000000</ROSN>
    <SLOV>50,000000</SLOV>
    <SVIZ>50,000000</SVIZ>
    <BSP>50,000000</BSP>
    <MALT>50,000000</MALT>
    <XAUS>50,000000</XAUS>
    <XFRA>50,000000</XFRA>
  </Prezzi>
  <Prezzi>
    <Data>20181107</Data>
    <Mercato>MGP</Mercato>
    <Ora>5</Ora>
    <PUN>51,370000</PUN>
    <NAT>51,370000</NAT>
    <CNOR>51,370000</CNOR>
    <CSUD>51,370000</CSUD>
    <NORD>51,370000</NORD>
    <SARD>51,370000</SARD>
    <SICI>51,370000</SICI>
    <SUD>51,370000</SUD>
    <AUST>51,370000</AUST>
    <BRNN>51,370000</BRNN>
    <COAC>51,370000</COAC>
    <CORS>51,370000</CORS>
    <FOGN>51,370000</FOGN>
    <FRAN>51,370000</FRAN>
    <GREC>51,370000</GREC>
    <MFTV>51,370000</MFTV>
    <PRGP>51,370000</PRGP>
    <ROSN>51,370000</ROSN>
    <SLOV>51,370000</SLOV>
    <SVIZ>51,370000</SVIZ>
    <BSP>51,370000</BSP>
    <MALT>51,370000</MALT>
    <XAUS>51,370000</XAUS>
    <XFRA>51,370000</XFRA>
  </Prezzi>
  <Prezzi>
    <Data>20181107</Data>
    <Mercato>MGP</Mercato>
    <Ora>6</Ora>
    <PUN>52,150000</PUN>
    <NAT>52,150000</NAT>
    <CNOR>52,150000</CNOR>
    <CSUD>52,150000</CSUD>
    <NORD>52,150000</NORD>
    <SARD>52,150000</SARD>
    <SICI>52,150000</SICI>
    <SUD>52,150000</SUD>
    <AUST>52,150000</AUST>
    <BRNN>52,150000</BRNN>
    <COAC>52,150000</COAC>
    <CORS>52,150000</CORS>
    <FOGN>52,150000</FOGN>
    <FRAN>52,150000</FRAN>
    <GREC>52,150000</GREC>
    <MFTV>52,150000</MFTV>
    <PRGP>52,150000</PRGP>
    <ROSN>52,150000</ROSN>
    <SLOV>52,150000</SLOV>
    <SVIZ>52,150000</SVIZ>
    <BSP>52,150000</BSP>
    <MALT>52,150000</MALT>
    <XAUS>52,150000</XAUS>
    <XFRA>52,150000</XFRA>
  </Prezzi>
  <Prezzi>
    <Data>20181107</Data>
    <Mercato>MGP</Mercato>
    <Ora>7</Ora>
    <PUN>57,190000</PUN>
    <NAT>57,190000</NAT>
    <CNOR>57,190000</CNOR>
    <CSUD>57,190000</CSUD>
    <NORD>57,190000</NORD>
    <SARD>57,190000</SARD>
    <SICI>57,190000</SICI>
    <SUD>57,190000</SUD>
    <AUST>57,190000</AUST>
    <BRNN>57,190000</BRNN>
    <COAC>57,190000</COAC>
    <CORS>57,190000</CORS>
    <FOGN>57,190000</FOGN>
    <FRAN>57,190000</FRAN>
    <GREC>57,190000</GREC>
    <MFTV>57,190000</MFTV>
    <PRGP>57,190000</PRGP>
    <ROSN>57,190000</ROSN>
    <SLOV>57,190000</SLOV>
    <SVIZ>57,190000</SVIZ>
    <BSP>57,190000</BSP>
    <MALT>57,190000</MALT>
    <XAUS>57,190000</XAUS>
    <XFRA>57,190000</XFRA>
  </Prezzi>
  <Prezzi>
    <Data>20181107</Data>
    <Mercato>MGP</Mercato>
    <Ora>8</Ora>
    <PUN>61,990000</PUN>
    <NAT>61,990000</NAT>
    <CNOR>61,990000</CNOR>
    <CSUD>61,990000</CSUD>
    <NORD>61,990000</NORD>
    <SARD>61,990000</SARD>
    <SICI>61,990000</SICI>
    <SUD>61,990000</SUD>
    <AUST>61,990000</AUST>
    <BRNN>61,990000</BRNN>
    <COAC>61,990000</COAC>
    <CORS>61,990000</CORS>
    <FOGN>61,990000</FOGN>
    <FRAN>61,990000</FRAN>
    <GREC>61,990000</GREC>
    <MFTV>61,990000</MFTV>
    <PRGP>61,990000</PRGP>
    <ROSN>61,990000</ROSN>
    <SLOV>61,990000</SLOV>
    <SVIZ>61,990000</SVIZ>
    <BSP>61,990000</BSP>
    <MALT>61,990000</MALT>
    <XAUS>61,990000</XAUS>
    <XFRA>61,990000</XFRA>
  </Prezzi>
  <Prezzi>
    <Data>20181107</Data>
    <Mercato>MGP</Mercato>
    <Ora>9</Ora>
    <PUN>66,000000</PUN>
    <NAT>66,000000</NAT>
    <CNOR>66,000000</CNOR>
    <CSUD>66,000000</CSUD>
    <NORD>66,000000</NORD>
    <SARD>66,000000</SARD>
    <SICI>66,000000</SICI>
    <SUD>66,000000</SUD>
    <AUST>66,000000</AUST>
    <BRNN>66,000000</BRNN>
    <COAC>66,000000</COAC>
    <CORS>66,000000</CORS>
    <FOGN>66,000000</FOGN>
    <FRAN>66,000000</FRAN>
    <GREC>66,000000</GREC>
    <MFTV>66,000000</MFTV>
    <PRGP>66,000000</PRGP>
    <ROSN>66,000000</ROSN>
    <SLOV>66,000000</SLOV>
    <SVIZ>66,000000</SVIZ>
    <BSP>66,000000</BSP>
    <MALT>66,000000</MALT>
    <XAUS>66,000000</XAUS>
    <XFRA>66,000000</XFRA>
  </Prezzi>
  <Prezzi>
    <Data>20181107</Data>
    <Mercato>MGP</Mercato>
    <Ora>10</Ora>
    <PUN>65,750000</PUN>
    <NAT>65,750000</NAT>
    <CNOR>65,750000</CNOR>
    <CSUD>65,750000</CSUD>
    <NORD>65,750000</NORD>
    <SARD>65,750000</SARD>
    <SICI>65,750000</SICI>
    <SUD>65,750000</SUD>
    <AUST>65,750000</AUST>
    <BRNN>65,750000</BRNN>
    <COAC>65,750000</COAC>
    <CORS>65,750000</CORS>
    <FOGN>65,750000</FOGN>
    <FRAN>65,750000</FRAN>
    <GREC>65,750000</GREC>
    <MFTV>65,750000</MFTV>
    <PRGP>65,750000</PRGP>
    <ROSN>65,750000</ROSN>
    <SLOV>65,750000</SLOV>
    <SVIZ>65,750000</SVIZ>
    <BSP>65,750000</BSP>
    <MALT>65,750000</MALT>
    <XAUS>65,750000</XAUS>
    <XFRA>65,750000</XFRA>
  </Prezzi>
  <Prezzi>
    <Data>20181107</Data>
    <Mercato>MGP</Mercato>
    <Ora>11</Ora>
    <PUN>63,840000</PUN>
    <NAT>63,840000</NAT>
    <CNOR>63,840000</CNOR>
    <CSUD>63,840000</CSUD>
    <NORD>63,840000</NORD>
    <SARD>63,840000</SARD>
    <SICI>63,840000</SICI>
    <SUD>63,840000</SUD>
    <AUST>63,840000</AUST>
    <BRNN>63,840000</BRNN>
    <COAC>63,840000</COAC>
    <CORS>63,840000</CORS>
    <FOGN>63,840000</FOGN>
    <FRAN>63,840000</FRAN>
    <GREC>63,840000</GREC>
    <MFTV>63,840000</MFTV>
    <PRGP>63,840000</PRGP>
    <ROSN>63,840000</ROSN>
    <SLOV>63,840000</SLOV>
    <SVIZ>63,840000</SVIZ>
    <BSP>63,840000</BSP>
    <MALT>63,840000</MALT>
    <XAUS>63,840000</XAUS>
    <XFRA>63,840000</XFRA>
  </Prezzi>
  <Prezzi>
    <Data>20181107</Data>
    <Mercato>MGP</Mercato>
    <Ora>12</Ora>
    <PUN>61,849780</PUN>
    <NAT>62,300000</NAT>
    <CNOR>62,300000</CNOR>
    <CSUD>62,300000</CSUD>
    <NORD>62,300000</NORD>
    <SARD>62,300000</SARD>
    <SICI>58,470000</SICI>
    <SUD>58,470000</SUD>
    <AUST>62,300000</AUST>
    <BRNN>58,470000</BRNN>
    <COAC>62,300000</COAC>
    <CORS>62,300000</CORS>
    <FOGN>58,470000</FOGN>
    <FRAN>62,300000</FRAN>
    <GREC>58,470000</GREC>
    <MFTV>62,300000</MFTV>
    <PRGP>58,470000</PRGP>
    <ROSN>58,470000</ROSN>
    <SLOV>62,300000</SLOV>
    <SVIZ>62,300000</SVIZ>
    <BSP>62,300000</BSP>
    <MALT>58,470000</MALT>
    <XAUS>62,300000</XAUS>
    <XFRA>62,300000</XFRA>
  </Prezzi>
  <Prezzi>
    <Data>20181107</Data>
    <Mercato>MGP</Mercato>
    <Ora>13</Ora>
    <PUN>59,777770</PUN>
    <NAT>58,620000</NAT>
    <CNOR>59,777770</CNOR>
    <CSUD>59,777770</CSUD>
    <NORD>59,777770</NORD>
    <SARD>59,777770</SARD>
    <SICI>59,777770</SICI>
    <SUD>59,777770</SUD>
    <AUST>59,777770</AUST>
    <BRNN>59,777770</BRNN>
    <COAC>59,777770</COAC>
    <CORS>59,777770</CORS>
    <FOGN>59,777770</FOGN>
    <FRAN>59,777770</FRAN>
    <GREC>59,777770</GREC>
    <MFTV>59,777770</MFTV>
    <PRGP>59,777770</PRGP>
    <ROSN>59,777770</ROSN>
    <SLOV>59,777770</SLOV>
    <SVIZ>59,777770</SVIZ>
    <BSP>59,777770</BSP>
    <MALT>59,777770</MALT>
    <XAUS>59,777770</XAUS>
    <XFRA>59,777770</XFRA>
  </Prezzi>
  <Prezzi>
    <Data>20181107</Data>
    <Mercato>MGP</Mercato>
    <Ora>14</Ora>
    <PUN>59,863980</PUN>
    <NAT>60,000000</NAT>
    <CNOR>60,029330</CNOR>
    <CSUD>60,029330</CSUD>
    <NORD>60,029330</NORD>
    <SARD>60,029330</SARD>
    <SICI>58,670000</SICI>
    <SUD>58,670000</SUD>
    <AUST>60,029330</AUST>
    <BRNN>58,670000</BRNN>
    <COAC>60,029330</COAC>
    <CORS>60,029330</CORS>
    <FOGN>58,670000</FOGN>
    <FRAN>60,029330</FRAN>
    <GREC>58,670000</GREC>
    <MFTV>60,029330</MFTV>
    <PRGP>58,670000</PRGP>
    <ROSN>58,670000</ROSN>
    <SLOV>60,029330</SLOV>
    <SVIZ>60,029330</SVIZ>
    <BSP>60,029330</BSP>
    <MALT>58,670000</MALT>
    <XAUS>60,029330</XAUS>
    <XFRA>60,029330</XFRA>
  </Prezzi>
  <Prezzi>
    <Data>20181107</Data>
    <Mercato>MGP</Mercato>
    <Ora>15</Ora>
    <PUN>62,943130</PUN>
    <NAT>62,400000</NAT>
    <CNOR>62,943130</CNOR>
    <CSUD>62,943130</CSUD>
    <NORD>62,943130</NORD>
    <SARD>62,943130</SARD>
    <SICI>62,943130</SICI>
    <SUD>62,943130</SUD>
    <AUST>62,943130</AUST>
    <BRNN>62,943130</BRNN>
    <COAC>62,943130</COAC>
    <CORS>62,943130</CORS>
    <FOGN>62,943130</FOGN>
    <FRAN>62,943130</FRAN>
    <GREC>62,943130</GREC>
    <MFTV>62,943130</MFTV>
    <PRGP>62,943130</PRGP>
    <ROSN>62,943130</ROSN>
    <SLOV>62,943130</SLOV>
    <SVIZ>62,943130</SVIZ>
    <BSP>62,943130</BSP>
    <MALT>62,943130</MALT>
    <XAUS>62,943130</XAUS>
    <XFRA>62,943130</XFRA>
  </Prezzi>
  <Prezzi>
    <Data>20181107</Data>
    <Mercato>MGP</Mercato>
    <Ora>16</Ora>
    <PUN>65,613270</PUN>
    <NAT>65,420000</NAT>
    <CNOR>65,613270</CNOR>
    <CSUD>65,613270</CSUD>
    <NORD>65,613270</NORD>
    <SARD>65,613270</SARD>
    <SICI>65,613270</SICI>
    <SUD>65,613270</SUD>
    <AUST>65,613270</AUST>
    <BRNN>65,613270</BRNN>
    <COAC>65,613270</COAC>
    <CORS>65,613270</CORS>
    <FOGN>65,613270</FOGN>
    <FRAN>65,613270</FRAN>
    <GREC>65,613270</GREC>
    <MFTV>65,613270</MFTV>
    <PRGP>65,613270</PRGP>
    <ROSN>65,613270</ROSN>
    <SLOV>65,613270</SLOV>
    <SVIZ>65,613270</SVIZ>
    <BSP>65,613270</BSP>
    <MALT>65,613270</MALT>
    <XAUS>65,613270</XAUS>
    <XFRA>65,613270</XFRA>
  </Prezzi>
  <Prezzi>
    <Data>20181107</Data>
    <Mercato>MGP</Mercato>
    <Ora>17</Ora>
    <PUN>68,030000</PUN>
    <NAT>68,030000</NAT>
    <CNOR>68,030000</CNOR>
    <CSUD>68,030000</CSUD>
    <NORD>68,030000</NORD>
    <SARD>68,030000</SARD>
    <SICI>68,030000</SICI>
    <SUD>68,030000</SUD>
    <AUST>68,030000</AUST>
    <BRNN>68,030000</BRNN>
    <COAC>68,030000</COAC>
    <CORS>68,030000</CORS>
    <FOGN>68,030000</FOGN>
    <FRAN>68,030000</FRAN>
    <GREC>68,030000</GREC>
    <MFTV>68,030000</MFTV>
    <PRGP>68,030000</PRGP>
    <ROSN>68,030000</ROSN>
    <SLOV>68,030000</SLOV>
    <SVIZ>68,030000</SVIZ>
    <BSP>68,030000</BSP>
    <MALT>68,030000</MALT>
    <XAUS>68,030000</XAUS>
    <XFRA>68,030000</XFRA>
  </Prezzi>
  <Prezzi>
    <Data>20181107</Data>
    <Mercato>MGP</Mercato>
    <Ora>18</Ora>
    <PUN>82,494410</PUN>
    <NAT>81,390000</NAT>
    <CNOR>82,470000</CNOR>
    <CSUD>82,470000</CSUD>
    <NORD>82,470000</NORD>
    <SARD>82,470000</SARD>
    <SICI>92,470000</SICI>
    <SUD>75,820000</SUD>
    <AUST>82,470000</AUST>
    <BRNN>75,820000</BRNN>
    <COAC>82,470000</COAC>
    <CORS>82,470000</CORS>
    <FOGN>75,820000</FOGN>
    <FRAN>82,470000</FRAN>
    <GREC>75,820000</GREC>
    <MFTV>82,470000</MFTV>
    <PRGP>92,470000</PRGP>
    <ROSN>75,820000</ROSN>
    <SLOV>82,470000</SLOV>
    <SVIZ>82,470000</SVIZ>
    <BSP>82,470000</BSP>
    <MALT>92,470000</MALT>
    <XAUS>82,470000</XAUS>
    <XFRA>82,470000</XFRA>
  </Prezzi>
  <Prezzi>
    <Data>20181107</Data>
    <Mercato>MGP</Mercato>
    <Ora>19</Ora>
    <PUN>75,441400</PUN>
    <NAT>75,700000</NAT>
    <CNOR>74,430000</CNOR>
    <CSUD>74,430000</CSUD>
    <NORD>74,430000</NORD>
    <SARD>74,430000</SARD>
    <SICI>92,470000</SICI>
    <SUD>74,430000</SUD>
    <AUST>74,430000</AUST>
    <BRNN>74,430000</BRNN>
    <COAC>74,430000</COAC>
    <CORS>74,430000</CORS>
    <FOGN>74,430000</FOGN>
    <FRAN>74,430000</FRAN>
    <GREC>74,430000</GREC>
    <MFTV>74,430000</MFTV>
    <PRGP>92,470000</PRGP>
    <ROSN>74,430000</ROSN>
    <SLOV>74,430000</SLOV>
    <SVIZ>74,430000</SVIZ>
    <BSP>74,430000</BSP>
    <MALT>92,470000</MALT>
    <XAUS>74,430000</XAUS>
    <XFRA>74,430000</XFRA>
  </Prezzi>
  <Prezzi>
    <Data>20181107</Data>
    <Mercato>MGP</Mercato>
    <Ora>20</Ora>
    <PUN>74,304530</PUN>
    <NAT>75,820000</NAT>
    <CNOR>73,089000</CNOR>
    <CSUD>73,089000</CSUD>
    <NORD>73,089000</NORD>
    <SARD>73,089000</SARD>
    <SICI>94,060000</SICI>
    <SUD>73,089000</SUD>
    <AUST>73,089000</AUST>
    <BRNN>73,089000</BRNN>
    <COAC>73,089000</COAC>
    <CORS>73,089000</CORS>
    <FOGN>73,089000</FOGN>
    <FRAN>73,089000</FRAN>
    <GREC>73,089000</GREC>
    <MFTV>73,089000</MFTV>
    <PRGP>94,060000</PRGP>
    <ROSN>73,089000</ROSN>
    <SLOV>73,089000</SLOV>
    <SVIZ>73,089000</SVIZ>
    <BSP>73,089000</BSP>
    <MALT>94,060000</MALT>
    <XAUS>73,089000</XAUS>
    <XFRA>73,089000</XFRA>
  </Prezzi>
  <Prezzi>
    <Data>20181107</Data>
    <Mercato>MGP</Mercato>
    <Ora>21</Ora>
    <PUN>65,401580</PUN>
    <NAT>65,380000</NAT>
    <CNOR>63,570000</CNOR>
    <CSUD>63,570000</CSUD>
    <NORD>63,570000</NORD>
    <SARD>63,570000</SARD>
    <SICI>94,060000</SICI>
    <SUD>63,570000</SUD>
    <AUST>63,570000</AUST>
    <BRNN>63,570000</BRNN>
    <COAC>63,570000</COAC>
    <CORS>63,570000</CORS>
    <FOGN>63,570000</FOGN>
    <FRAN>63,570000</FRAN>
    <GREC>63,570000</GREC>
    <MFTV>63,570000</MFTV>
    <PRGP>94,060000</PRGP>
    <ROSN>63,570000</ROSN>
    <SLOV>63,570000</SLOV>
    <SVIZ>63,570000</SVIZ>
    <BSP>63,570000</BSP>
    <MALT>94,060000</MALT>
    <XAUS>63,570000</XAUS>
    <XFRA>63,570000</XFRA>
  </Prezzi>
  <Prezzi>
    <Data>20181107</Data>
    <Mercato>MGP</Mercato>
    <Ora>22</Ora>
    <PUN>60,059110</PUN>
    <NAT>59,290000</NAT>
    <CNOR>58,000000</CNOR>
    <CSUD>58,000000</CSUD>
    <NORD>58,000000</NORD>
    <SARD>58,000000</SARD>
    <SICI>92,470000</SICI>
    <SUD>58,000000</SUD>
    <AUST>58,000000</AUST>
    <BRNN>58,000000</BRNN>
    <COAC>58,000000</COAC>
    <CORS>58,000000</CORS>
    <FOGN>58,000000</FOGN>
    <FRAN>58,000000</FRAN>
    <GREC>58,000000</GREC>
    <MFTV>58,000000</MFTV>
    <PRGP>92,470000</PRGP>
    <ROSN>58,000000</ROSN>
    <SLOV>58,000000</SLOV>
    <SVIZ>58,000000</SVIZ>
    <BSP>58,000000</BSP>
    <MALT>92,470000</MALT>
    <XAUS>58,000000</XAUS>
    <XFRA>58,000000</XFRA>
  </Prezzi>
  <Prezzi>
    <Data>20181107</Data>
    <Mercato>MGP</Mercato>
    <Ora>23</Ora>
    <PUN>57,130050</PUN>
    <NAT>55,970000</NAT>
    <CNOR>55,190000</CNOR>
    <CSUD>55,190000</CSUD>
    <NORD>55,190000</NORD>
    <SARD>55,190000</SARD>
    <SICI>87,470000</SICI>
    <SUD>55,190000</SUD>
    <AUST>55,190000</AUST>
    <BRNN>55,190000</BRNN>
    <COAC>55,190000</COAC>
    <CORS>55,190000</CORS>
    <FOGN>55,190000</FOGN>
    <FRAN>55,190000</FRAN>
    <GREC>55,190000</GREC>
    <MFTV>55,190000</MFTV>
    <PRGP>87,470000</PRGP>
    <ROSN>55,190000</ROSN>
    <SLOV>55,190000</SLOV>
    <SVIZ>55,190000</SVIZ>
    <BSP>55,190000</BSP>
    <MALT>87,470000</MALT>
    <XAUS>55,190000</XAUS>
    <XFRA>55,190000</XFRA>
  </Prezzi>
  <Prezzi>
    <Data>20181107</Data>
    <Mercato>MGP</Mercato>
    <Ora>24</Ora>
    <PUN>52,749880</PUN>
    <NAT>52,150000</NAT>
    <CNOR>52,031980</CNOR>
    <CSUD>52,031980</CSUD>
    <NORD>52,031980</NORD>
    <SARD>52,031980</SARD>
    <SICI>64,180000</SICI>
    <SUD>52,031980</SUD>
    <AUST>52,031980</AUST>
    <BRNN>52,031980</BRNN>
    <COAC>52,031980</COAC>
    <CORS>52,031980</CORS>
    <FOGN>52,031980</FOGN>
    <FRAN>52,031980</FRAN>
    <GREC>52,031980</GREC>
    <MFTV>52,031980</MFTV>
    <PRGP>64,180000</PRGP>
    <ROSN>52,031980</ROSN>
    <SLOV>52,031980</SLOV>
    <SVIZ>52,031980</SVIZ>
    <BSP>52,031980</BSP>
    <MALT>64,180000</MALT>
    <XAUS>52,031980</XAUS>
    <XFRA>52,031980</XFRA>
  </Prezzi>
</NewDataSet>